{
  "id": "seiyuu-radio-no-uraomote",
  "title": "انمي Seiyuu Radio no Uraomote مترجم اون لاين",
  "url": "https://animelek.top/anime/seiyuu-radio-no-uraomote/",
  "poster": "data/posters/seiyuu-radio-no-uraomote.webp",
  "status": "مكتمل",
  "type": "تلفزيون",
  "episodes_count": "12",
  "start_date": "2024",
  "season": "ربيع 2024",
  "genres": [
    "دراما",
    "كوميدي"
  ],
  "story": "قصة انمي Seiyuu Radio no Uraomote تدور حول “واتانابي تشيكا” و “ساتو يوميكو“، مؤديتا صوت من المدرسة الثانوية تصادف أنهما التحقتا بنفس المدرسة وتم وضعهما بالصدفة في نفس الفصل، هما المضيفان لبرنامج إذاعي أسبوعي. بصفتهم زملاء في الفصل ومؤديات صوت، فإنهم يظهرون صداقتهم العظيمة لجميع المستمعين! على الأقل، سطحيا. في الواقع، الفتاة الهادئة “تشيكا” على عكس “يوميكو” تماما. وهما بالتأكيد لا يستطيعون تحمل بعضهم البعض. فخارج البث، تندلع الفوضى والشتائم. بينما على الهواء، هم أفضل الأصدقاء. لكن إلى أين ستقودهم هذه العلاقة المضطربة ؟",
  "episodes": [
    {
      "number": "12",
      "title": "الحلقة 12Seiyuu Radio no Uraomote",
      "date": "26 يونيو, 2024",
      "servers": [
        {
          "name": "megamax me | HD",
          "embed_url": "https://animelek.top/card.php?random=https://megamax.me/iframe/tzRZyESNZu2lH"
        },
        {
          "name": "leech megamax | HD",
          "embed_url": "https://animelek.top/card.php?random=https://leech.megamax.me/e/tzRZyESNZu2lH"
        },
        {
          "name": "megamax me | HD",
          "embed_url": "https://animelek.top/card.php?random=https://megamax.me/iframe/tzRZyESNZu2lH"
        },
        {
          "name": "segavid | HD",
          "embed_url": "https://animelek.top/card.php?random=https://segavid.com/embed-pu5pxho6brc3.html"
        },
        {
          "name": "vidmoly to | HD",
          "embed_url": "https://animelek.top/card.php?random=//vidmoly.to/embed-tf43jgkz58bq.html"
        },
        {
          "name": "uqload to | HD",
          "embed_url": "https://animelek.top/card.php?random=https://uqload.to/embed-2o2qz4px01mv.html"
        },
        {
          "name": "ok ru | HD",
          "embed_url": "https://animelek.top/card.php?random=https://www.ok.ru/videoembed/7047326730970"
        },
        {
          "name": "mp4upload | HD",
          "embed_url": "https://animelek.top/card.php?random=https://www.mp4upload.com/embed-5m2vo9i7ac7g.html"
        },
        {
          "name": "mega | HD",
          "embed_url": "https://animelek.top/card.php?random=https://mega.nz/embed/dC0RGDjS!_qcRyI0eCqd8WNf2Od5fpbOfKMexpub77j3h3fySG9c"
        },
        {
          "name": "sendvid | HD",
          "embed_url": "https://animelek.top/card.php?random=https://sendvid.com/embed/owvrk3zl"
        },
        {
          "name": "ok ru | FHD",
          "embed_url": "https://animelek.top/card.php?random=https://www.ok.ru/videoembed/7047312706266"
        },
        {
          "name": "mp4upload | FHD",
          "embed_url": "https://animelek.top/card.php?random=https://www.mp4upload.com/embed-bli76kesinlo.html"
        },
        {
          "name": "mega | FHD",
          "embed_url": "https://animelek.top/card.php?random=https://mega.nz/embed/JbEmjDaC!Y9ssvhdh5zJcgsDK4AxafjCTsf9BsSWyF1XABwSc_gk"
        },
        {
          "name": "ok ru | SD",
          "embed_url": "https://animelek.top/card.php?random=https://www.ok.ru/videoembed/7047330532058"
        },
        {
          "name": "mp4upload | SD",
          "embed_url": "https://animelek.top/card.php?random=https://www.mp4upload.com/embed-bj6yk1h0c4py.html"
        },
        {
          "name": "mega | SD",
          "embed_url": "https://animelek.top/card.php?random=https://mega.nz/embed/UK0WmBRZ!4-2IJ67d0uHvrYyZxtOwJWsKwRUhqAqx4DOIlAasfm8"
        }
      ],
      "downloads": [
        {
          "server": "file-upload",
          "quality": "480p",
          "language": "مترجم",
          "url": "https://www.file-upload.org/j5ngqt9t78y7"
        },
        {
          "server": "mp4upload",
          "quality": "480p",
          "language": "مترجم",
          "url": "https://www.mp4upload.com/bj6yk1h0c4py"
        },
        {
          "server": "mega",
          "quality": "480p",
          "language": "مترجم",
          "url": "https://mega.nz/#!UK0WmBRZ!4-2IJ67d0uHvrYyZxtOwJWsKwRUhqAqx4DOIlAasfm8"
        },
        {
          "server": "uupbom",
          "quality": "480p",
          "language": "مترجم",
          "url": "http://uupbom.com/kwcbo0c2p8u0"
        },
        {
          "server": "updown",
          "quality": "480p",
          "language": "مترجم",
          "url": "https://updown.cam/nzzmfhvatouv"
        },
        {
          "server": "file-upload",
          "quality": "720p",
          "language": "مترجم",
          "url": "https://www.file-upload.org/et5jtj7uvet6"
        },
        {
          "server": "mp4upload",
          "quality": "720p",
          "language": "مترجم",
          "url": "https://www.mp4upload.com/5m2vo9i7ac7g"
        },
        {
          "server": "mega",
          "quality": "720p",
          "language": "مترجم",
          "url": "https://mega.nz/#!dC0RGDjS!_qcRyI0eCqd8WNf2Od5fpbOfKMexpub77j3h3fySG9c"
        },
        {
          "server": "uupbom",
          "quality": "720p",
          "language": "مترجم",
          "url": "http://uupbom.com/x5vzak4n991w"
        },
        {
          "server": "updown",
          "quality": "720p",
          "language": "مترجم",
          "url": "https://updown.cam/lzc7ug5lpkeq"
        },
        {
          "server": "file-upload",
          "quality": "1080p",
          "language": "مترجم",
          "url": "https://www.file-upload.org/1zrgzc6fx1mr"
        },
        {
          "server": "mp4upload",
          "quality": "1080p",
          "language": "مترجم",
          "url": "https://www.mp4upload.com/bli76kesinlo"
        },
        {
          "server": "mega",
          "quality": "1080p",
          "language": "مترجم",
          "url": "https://mega.nz/#!JbEmjDaC!Y9ssvhdh5zJcgsDK4AxafjCTsf9BsSWyF1XABwSc_gk"
        },
        {
          "server": "uupbom",
          "quality": "1080p",
          "language": "مترجم",
          "url": "http://uupbom.com/b4uiphwk3czl"
        },
        {
          "server": "updown",
          "quality": "1080p",
          "language": "مترجم",
          "url": "https://updown.cam/j6n113xr3uno"
        }
      ]
    },
    {
      "number": "10",
      "title": "الحلقة 10Seiyuu Radio no Uraomote",
      "date": "22 يونيو, 2024",
      "servers": [
        {
          "name": "megamax me | HD",
          "embed_url": "https://animelek.top/card.php?random=https://megamax.me/iframe/nb0zDYCQqC0hZ"
        },
        {
          "name": "leech megamax | HD",
          "embed_url": "https://animelek.top/card.php?random=https://leech.megamax.me/e/nb0zDYCQqC0hZ"
        },
        {
          "name": "megamax me | HD",
          "embed_url": "https://animelek.top/card.php?random=https://megamax.me/iframe/nb0zDYCQqC0hZ"
        },
        {
          "name": "segavid | HD",
          "embed_url": "https://animelek.top/card.php?random=https://segavid.com/embed-cz56wf5pa3eo.html"
        },
        {
          "name": "vidmoly to | HD",
          "embed_url": "https://animelek.top/card.php?random=//vidmoly.to/embed-h3o5i3mi0hjj.html"
        },
        {
          "name": "uqload to | HD",
          "embed_url": "https://animelek.top/card.php?random=https://uqload.to/embed-bxo6xlzvqln1.html"
        },
        {
          "name": "ok ru | HD",
          "embed_url": "https://animelek.top/card.php?random=https://www.ok.ru/videoembed/7007551752922"
        },
        {
          "name": "mp4upload | HD",
          "embed_url": "https://animelek.top/card.php?random=https://www.mp4upload.com/embed-jilv7l8k3cyb.html"
        },
        {
          "name": "mega | HD",
          "embed_url": "https://animelek.top/card.php?random=https://mega.nz/embed/c3NyEKAZ!2wWOoVqOoF1ip3wQwIq9UIdRM634QMt6ea7fnQiBQQc"
        },
        {
          "name": "sendvid | HD",
          "embed_url": "https://animelek.top/card.php?random=https://sendvid.com/embed/94hb9114"
        },
        {
          "name": "ok ru | FHD",
          "embed_url": "https://animelek.top/card.php?random=https://www.ok.ru/videoembed/7007544216282"
        },
        {
          "name": "mp4upload | FHD",
          "embed_url": "https://animelek.top/card.php?random=https://www.mp4upload.com/embed-e28ccot1szws.html"
        },
        {
          "name": "mega | FHD",
          "embed_url": "https://animelek.top/card.php?random=https://mega.nz/embed/EnkAFJCA!H-QsT1-0QWMScPb3TU-HyhDY4x75zeNfgjUsUgYNtNw"
        },
        {
          "name": "ok ru | SD",
          "embed_url": "https://animelek.top/card.php?random=https://www.ok.ru/videoembed/7007559420634"
        },
        {
          "name": "mp4upload | SD",
          "embed_url": "https://animelek.top/card.php?random=https://www.mp4upload.com/embed-9u7nga0lky42.html"
        },
        {
          "name": "mega | SD",
          "embed_url": "https://animelek.top/card.php?random=https://mega.nz/embed/52UUAYrR!m4Jbs8jdZPa4kfl47C4cHlDiWSVoswJx_alGG-tehUA"
        }
      ],
      "downloads": [
        {
          "server": "mp4upload",
          "quality": "480p",
          "language": "مترجم",
          "url": "https://www.mp4upload.com/9u7nga0lky42"
        },
        {
          "server": "file-upload",
          "quality": "480p",
          "language": "مترجم",
          "url": "https://www.file-upload.org/uwht0hu83nyd"
        },
        {
          "server": "mega",
          "quality": "480p",
          "language": "مترجم",
          "url": "https://mega.nz/#!52UUAYrR!m4Jbs8jdZPa4kfl47C4cHlDiWSVoswJx_alGG-tehUA"
        },
        {
          "server": "uupbom",
          "quality": "480p",
          "language": "مترجم",
          "url": "http://uupbom.com/0ovjtp8n7p7e"
        },
        {
          "server": "mp4upload",
          "quality": "720p",
          "language": "مترجم",
          "url": "https://www.mp4upload.com/jilv7l8k3cyb"
        },
        {
          "server": "file-upload",
          "quality": "720p",
          "language": "مترجم",
          "url": "https://www.file-upload.org/8skhrbp1xt1i"
        },
        {
          "server": "mega",
          "quality": "720p",
          "language": "مترجم",
          "url": "https://mega.nz/#!c3NyEKAZ!2wWOoVqOoF1ip3wQwIq9UIdRM634QMt6ea7fnQiBQQc"
        },
        {
          "server": "uupbom",
          "quality": "720p",
          "language": "مترجم",
          "url": "http://uupbom.com/f7xwq21weq91"
        },
        {
          "server": "mp4upload",
          "quality": "1080p",
          "language": "مترجم",
          "url": "https://www.mp4upload.com/e28ccot1szws"
        },
        {
          "server": "file-upload",
          "quality": "1080p",
          "language": "مترجم",
          "url": "https://www.file-upload.org/pr4nfi3w586z"
        },
        {
          "server": "mega",
          "quality": "1080p",
          "language": "مترجم",
          "url": "https://mega.nz/#!EnkAFJCA!H-QsT1-0QWMScPb3TU-HyhDY4x75zeNfgjUsUgYNtNw"
        },
        {
          "server": "uupbom",
          "quality": "1080p",
          "language": "مترجم",
          "url": "http://uupbom.com/0oxutogaj2jx"
        }
      ]
    },
    {
      "number": "9",
      "title": "الحلقة 9Seiyuu Radio no Uraomote",
      "date": "22 يونيو, 2024",
      "servers": [
        {
          "name": "megamax me | HD",
          "embed_url": "https://animelek.top/card.php?random=https://megamax.me/iframe/pffzn55O5pEQH"
        },
        {
          "name": "leech megamax | HD",
          "embed_url": "https://animelek.top/card.php?random=https://leech.megamax.me/e/pffzn55O5pEQH"
        },
        {
          "name": "megamax me | HD",
          "embed_url": "https://animelek.top/card.php?random=https://megamax.me/iframe/pffzn55O5pEQH"
        },
        {
          "name": "segavid | HD",
          "embed_url": "https://animelek.top/card.php?random=https://segavid.com/embed-iuw0z7z1if87.html"
        },
        {
          "name": "vidmoly to | HD",
          "embed_url": "https://animelek.top/card.php?random=//vidmoly.to/embed-4qz6lxwc7pgz.html"
        },
        {
          "name": "uqload to | HD",
          "embed_url": "https://animelek.top/card.php?random=https://uqload.to/embed-226hbz5f6yfj.html"
        },
        {
          "name": "ok ru | HD",
          "embed_url": "https://animelek.top/card.php?random=https://www.ok.ru/videoembed/6985681799898"
        },
        {
          "name": "mp4upload | HD",
          "embed_url": "https://animelek.top/card.php?random=https://www.mp4upload.com/embed-3mzz8h0r04ib.html"
        },
        {
          "name": "mega | HD",
          "embed_url": "https://animelek.top/card.php?random=https://mega.nz/embed/WTZRhJQa!YIeQf16rJ1mPYZkjv8tm0X4LP0CVB4hOYs-J0b1oyBk"
        },
        {
          "name": "sendvid | HD",
          "embed_url": "https://animelek.top/card.php?random=https://sendvid.com/embed/phvpcwjd"
        },
        {
          "name": "ok ru | FHD",
          "embed_url": "https://animelek.top/card.php?random=https://www.ok.ru/videoembed/6985675442906"
        },
        {
          "name": "mp4upload | FHD",
          "embed_url": "https://animelek.top/card.php?random=https://www.mp4upload.com/embed-bwvhg70ao3dh.html"
        },
        {
          "name": "mega | FHD",
          "embed_url": "https://animelek.top/card.php?random=https://mega.nz/embed/PKRhGZ4A!GBb0J71vsktEqhjWD7JrcxKJF6b6keRWdYuvdCBv5OQ"
        },
        {
          "name": "ok ru | SD",
          "embed_url": "https://animelek.top/card.php?random=https://www.ok.ru/videoembed/6985688156890"
        },
        {
          "name": "mp4upload | SD",
          "embed_url": "https://animelek.top/card.php?random=https://www.mp4upload.com/embed-p0y1bk89zueg.html"
        },
        {
          "name": "mega | SD",
          "embed_url": "https://animelek.top/card.php?random=https://mega.nz/embed/fGBBQYBZ!CC5DQe8iwLIR68Q0FCanxUD4NmQnwsbGs9uHXJAyBAg"
        }
      ],
      "downloads": [
        {
          "server": "file-upload",
          "quality": "480p",
          "language": "مترجم",
          "url": "https://www.file-upload.org/irn7n1xkt0kg"
        },
        {
          "server": "mp4upload",
          "quality": "480p",
          "language": "مترجم",
          "url": "https://www.mp4upload.com/p0y1bk89zueg"
        },
        {
          "server": "mega",
          "quality": "480p",
          "language": "مترجم",
          "url": "https://mega.nz/#!fGBBQYBZ!CC5DQe8iwLIR68Q0FCanxUD4NmQnwsbGs9uHXJAyBAg"
        },
        {
          "server": "uupbom",
          "quality": "480p",
          "language": "مترجم",
          "url": "http://uupbom.com/6ct8viorjgw3"
        },
        {
          "server": "updown",
          "quality": "480p",
          "language": "مترجم",
          "url": "https://updown.cam/l2nwon90e522"
        },
        {
          "server": "file-upload",
          "quality": "720p",
          "language": "مترجم",
          "url": "https://www.file-upload.org/c9tut8flgfx2"
        },
        {
          "server": "mp4upload",
          "quality": "720p",
          "language": "مترجم",
          "url": "https://www.mp4upload.com/3mzz8h0r04ib"
        },
        {
          "server": "mega",
          "quality": "720p",
          "language": "مترجم",
          "url": "https://mega.nz/#!WTZRhJQa!YIeQf16rJ1mPYZkjv8tm0X4LP0CVB4hOYs-J0b1oyBk"
        },
        {
          "server": "uupbom",
          "quality": "720p",
          "language": "مترجم",
          "url": "http://uupbom.com/w8qg01ruifqd"
        },
        {
          "server": "updown",
          "quality": "720p",
          "language": "مترجم",
          "url": "https://updown.cam/3fmks2jkthfs"
        },
        {
          "server": "file-upload",
          "quality": "1080p",
          "language": "مترجم",
          "url": "https://www.file-upload.org/d4gj6eglanmz"
        },
        {
          "server": "mp4upload",
          "quality": "1080p",
          "language": "مترجم",
          "url": "https://www.mp4upload.com/bwvhg70ao3dh"
        },
        {
          "server": "mega",
          "quality": "1080p",
          "language": "مترجم",
          "url": "https://mega.nz/#!PKRhGZ4A!GBb0J71vsktEqhjWD7JrcxKJF6b6keRWdYuvdCBv5OQ"
        },
        {
          "server": "uupbom",
          "quality": "1080p",
          "language": "مترجم",
          "url": "http://uupbom.com/tsvp4xc25a28"
        },
        {
          "server": "updown",
          "quality": "1080p",
          "language": "مترجم",
          "url": "https://updown.cam/jzbmfjixgve4"
        }
      ]
    },
    {
      "number": "11",
      "title": "الحلقة 11Seiyuu Radio no Uraomote",
      "date": "22 يونيو, 2024",
      "servers": [
        {
          "name": "megamax me | HD",
          "embed_url": "https://animelek.top/card.php?random=https://megamax.me/iframe/qqBPjLaSRczKU"
        },
        {
          "name": "leech megamax | HD",
          "embed_url": "https://animelek.top/card.php?random=https://leech.megamax.me/e/qqBPjLaSRczKU"
        },
        {
          "name": "megamax me | HD",
          "embed_url": "https://animelek.top/card.php?random=https://megamax.me/iframe/qqBPjLaSRczKU"
        },
        {
          "name": "segavid | HD",
          "embed_url": "https://animelek.top/card.php?random=https://segavid.com/embed-utdll9gmivyh.html"
        },
        {
          "name": "vidmoly to | HD",
          "embed_url": "https://animelek.top/card.php?random=//vidmoly.to/embed-avptnczvrsk7.html"
        },
        {
          "name": "ok ru | HD",
          "embed_url": "https://animelek.top/card.php?random=https://www.ok.ru/videoembed/7028095716058"
        },
        {
          "name": "mp4upload | HD",
          "embed_url": "https://animelek.top/card.php?random=https://www.mp4upload.com/embed-73a7dseew6iq.html"
        },
        {
          "name": "mega | HD",
          "embed_url": "https://animelek.top/card.php?random=https://mega.nz/embed/RykVUTKD!vtKqOwgkNoQAy_geZeup-lkLlp8h8NjbCm4WNIk5s-g"
        },
        {
          "name": "sendvid | HD",
          "embed_url": "https://animelek.top/card.php?random=https://sendvid.com/embed/7j1nxkvd"
        },
        {
          "name": "ok ru | FHD",
          "embed_url": "https://animelek.top/card.php?random=https://www.ok.ru/videoembed/7028081887962"
        },
        {
          "name": "mp4upload | FHD",
          "embed_url": "https://animelek.top/card.php?random=https://www.mp4upload.com/embed-l2fem5rg0ygi.html"
        },
        {
          "name": "mega | FHD",
          "embed_url": "https://animelek.top/card.php?random=https://mega.nz/embed/wiED0ZaR!GPRNVjEiMkprTukp8xIPU1iOdPMiSxSp7KQIE7TiJCI"
        },
        {
          "name": "ok ru | SD",
          "embed_url": "https://animelek.top/card.php?random=https://www.ok.ru/videoembed/7028103318234"
        },
        {
          "name": "mp4upload | SD",
          "embed_url": "https://animelek.top/card.php?random=https://www.mp4upload.com/embed-ohdhl02ic20i.html"
        },
        {
          "name": "mega | SD",
          "embed_url": "https://animelek.top/card.php?random=https://mega.nz/embed/9jkF0YqB!0wBQ5ZC-4Pp3EwYF8kAhv6aVx5LSjw6esorJV7tVxxc"
        }
      ],
      "downloads": [
        {
          "server": "mp4upload",
          "quality": "480p",
          "language": "مترجم",
          "url": "https://www.mp4upload.com/ohdhl02ic20i"
        },
        {
          "server": "file-upload",
          "quality": "480p",
          "language": "مترجم",
          "url": "https://www.file-upload.org/8rfd5f1tgkev"
        },
        {
          "server": "mega",
          "quality": "480p",
          "language": "مترجم",
          "url": "https://mega.nz/#!9jkF0YqB!0wBQ5ZC-4Pp3EwYF8kAhv6aVx5LSjw6esorJV7tVxxc"
        },
        {
          "server": "uupbom",
          "quality": "480p",
          "language": "مترجم",
          "url": "http://uupbom.com/hn7b4vt15u5z"
        },
        {
          "server": "updown",
          "quality": "480p",
          "language": "مترجم",
          "url": "https://updown.cam/foxkn11dpvey"
        },
        {
          "server": "file-upload",
          "quality": "720p",
          "language": "مترجم",
          "url": "https://www.file-upload.org/2o97452673op"
        },
        {
          "server": "mp4upload",
          "quality": "720p",
          "language": "مترجم",
          "url": "https://www.mp4upload.com/73a7dseew6iq"
        },
        {
          "server": "mega",
          "quality": "720p",
          "language": "مترجم",
          "url": "https://mega.nz/#!RykVUTKD!vtKqOwgkNoQAy_geZeup-lkLlp8h8NjbCm4WNIk5s-g"
        },
        {
          "server": "uupbom",
          "quality": "720p",
          "language": "مترجم",
          "url": "http://uupbom.com/fjs1tncqc1fl"
        },
        {
          "server": "updown",
          "quality": "720p",
          "language": "مترجم",
          "url": "https://updown.cam/o9z7gpe7nbth"
        },
        {
          "server": "file-upload",
          "quality": "1080p",
          "language": "مترجم",
          "url": "https://www.file-upload.org/30xax3879ssp"
        },
        {
          "server": "mp4upload",
          "quality": "1080p",
          "language": "مترجم",
          "url": "https://www.mp4upload.com/l2fem5rg0ygi"
        },
        {
          "server": "mega",
          "quality": "1080p",
          "language": "مترجم",
          "url": "https://mega.nz/#!wiED0ZaR!GPRNVjEiMkprTukp8xIPU1iOdPMiSxSp7KQIE7TiJCI"
        },
        {
          "server": "uupbom",
          "quality": "1080p",
          "language": "مترجم",
          "url": "http://uupbom.com/xb6maqzq3brr"
        },
        {
          "server": "updown",
          "quality": "1080p",
          "language": "مترجم",
          "url": "https://updown.cam/o8dk1kzdx1dc"
        }
      ]
    },
    {
      "number": "8",
      "title": "الحلقة 8Seiyuu Radio no Uraomote",
      "date": "22 يونيو, 2024",
      "servers": [
        {
          "name": "megamax me | HD",
          "embed_url": "https://animelek.top/card.php?random=https://megamax.me/iframe/raBThAyMZXyej"
        },
        {
          "name": "leech megamax | HD",
          "embed_url": "https://animelek.top/card.php?random=https://leech.megamax.me/e/raBThAyMZXyej"
        },
        {
          "name": "megamax me | HD",
          "embed_url": "https://animelek.top/card.php?random=https://megamax.me/iframe/raBThAyMZXyej"
        },
        {
          "name": "segavid | HD",
          "embed_url": "https://animelek.top/card.php?random=https://segavid.com/embed-yzmyc0w18owq.html"
        },
        {
          "name": "vidmoly to | HD",
          "embed_url": "https://animelek.top/card.php?random=//vidmoly.to/embed-rndj1f9d6e9o.html"
        },
        {
          "name": "uqload to | HD",
          "embed_url": "https://animelek.top/card.php?random=https://uqload.to/embed-ekafof50jtk4.html"
        },
        {
          "name": "ok ru | HD",
          "embed_url": "https://animelek.top/card.php?random=https://www.ok.ru/videoembed/6964548209370"
        },
        {
          "name": "mp4upload | HD",
          "embed_url": "https://animelek.top/card.php?random=https://www.mp4upload.com/embed-j0l5a3xy6u61.html"
        },
        {
          "name": "mega | HD",
          "embed_url": "https://animelek.top/card.php?random=https://mega.nz/embed/56lUkIqK!ixRzLI36xKYlB1xiMHqNej35PUPXsZk1B-gowqQEQFM"
        },
        {
          "name": "sendvid | HD",
          "embed_url": "https://animelek.top/card.php?random=https://sendvid.com/embed/anhzzjzs"
        },
        {
          "name": "ok ru | FHD",
          "embed_url": "https://animelek.top/card.php?random=https://www.ok.ru/videoembed/6964544932570"
        },
        {
          "name": "mp4upload | FHD",
          "embed_url": "https://animelek.top/card.php?random=https://www.mp4upload.com/embed-67pled6xgzzq.html"
        },
        {
          "name": "mega | FHD",
          "embed_url": "https://animelek.top/card.php?random=https://mega.nz/embed/cyEiHRAL!eTW_6O58GUXSV3e3pcfwd0XC49dqUC574WsNqAJZHxE"
        },
        {
          "name": "ok ru | SD",
          "embed_url": "https://animelek.top/card.php?random=https://www.ok.ru/videoembed/6964551355098"
        },
        {
          "name": "mp4upload | SD",
          "embed_url": "https://animelek.top/card.php?random=https://www.mp4upload.com/embed-bmcin6cjylvd.html"
        },
        {
          "name": "mega | SD",
          "embed_url": "https://animelek.top/card.php?random=https://mega.nz/embed/dqdWjDJK!Jl0y8IC3WVGiHyVGsmzhbV-qJBpjtNpD53pu6viTTA0"
        }
      ],
      "downloads": [
        {
          "server": "file-upload",
          "quality": "480p",
          "language": "مترجم",
          "url": "https://www.file-upload.org/2ttpsq6457s8"
        },
        {
          "server": "mp4upload",
          "quality": "480p",
          "language": "مترجم",
          "url": "https://www.mp4upload.com/bmcin6cjylvd"
        },
        {
          "server": "mega",
          "quality": "480p",
          "language": "مترجم",
          "url": "https://mega.nz/#!dqdWjDJK!Jl0y8IC3WVGiHyVGsmzhbV-qJBpjtNpD53pu6viTTA0"
        },
        {
          "server": "uupbom",
          "quality": "480p",
          "language": "مترجم",
          "url": "http://uupbom.com/w108wxdum8o2"
        },
        {
          "server": "updown",
          "quality": "480p",
          "language": "مترجم",
          "url": "https://updown.cam/jprv4ovy6vf7"
        },
        {
          "server": "file-upload",
          "quality": "720p",
          "language": "مترجم",
          "url": "https://www.file-upload.org/n7xkcaxdqm1t"
        },
        {
          "server": "mp4upload",
          "quality": "720p",
          "language": "مترجم",
          "url": "https://www.mp4upload.com/j0l5a3xy6u61"
        },
        {
          "server": "mega",
          "quality": "720p",
          "language": "مترجم",
          "url": "https://mega.nz/#!56lUkIqK!ixRzLI36xKYlB1xiMHqNej35PUPXsZk1B-gowqQEQFM"
        },
        {
          "server": "uupbom",
          "quality": "720p",
          "language": "مترجم",
          "url": "http://uupbom.com/vyapf3p8azmf"
        },
        {
          "server": "updown",
          "quality": "720p",
          "language": "مترجم",
          "url": "https://updown.cam/ha25b72sh6xp"
        },
        {
          "server": "file-upload",
          "quality": "1080p",
          "language": "مترجم",
          "url": "https://www.file-upload.org/9uiv44caceq9"
        },
        {
          "server": "mp4upload",
          "quality": "1080p",
          "language": "مترجم",
          "url": "https://www.mp4upload.com/67pled6xgzzq"
        },
        {
          "server": "mega",
          "quality": "1080p",
          "language": "مترجم",
          "url": "https://mega.nz/#!cyEiHRAL!eTW_6O58GUXSV3e3pcfwd0XC49dqUC574WsNqAJZHxE"
        },
        {
          "server": "uupbom",
          "quality": "1080p",
          "language": "مترجم",
          "url": "http://uupbom.com/v6jjsiu8bdfr"
        },
        {
          "server": "updown",
          "quality": "1080p",
          "language": "مترجم",
          "url": "https://updown.cam/0rzavpwjeha8"
        }
      ]
    },
    {
      "number": "6",
      "title": "الحلقة 6Seiyuu Radio no Uraomote",
      "date": "22 يونيو, 2024",
      "servers": [
        {
          "name": "megamax me | HD",
          "embed_url": "https://animelek.top/card.php?random=https://megamax.me/iframe/N1dgg7evSdKVW"
        },
        {
          "name": "leech megamax | HD",
          "embed_url": "https://animelek.top/card.php?random=https://leech.megamax.me/e/N1dgg7evSdKVW"
        },
        {
          "name": "megamax me | HD",
          "embed_url": "https://animelek.top/card.php?random=https://megamax.me/iframe/N1dgg7evSdKVW"
        },
        {
          "name": "segavid | HD",
          "embed_url": "https://animelek.top/card.php?random=https://segavid.com/embed-8grifvzfmb5u.html"
        },
        {
          "name": "vidmoly to | HD",
          "embed_url": "https://animelek.top/card.php?random=//vidmoly.to/embed-7ipe84z5a0on.html"
        },
        {
          "name": "uqload to | HD",
          "embed_url": "https://animelek.top/card.php?random=https://uqload.to/embed-mw7ua45jzhp9.html"
        },
        {
          "name": "ok ru | HD",
          "embed_url": "https://animelek.top/card.php?random=https://www.ok.ru/videoembed/6921099545306"
        },
        {
          "name": "mp4upload | HD",
          "embed_url": "https://animelek.top/card.php?random=https://www.mp4upload.com/embed-ohqi8xw7qo5f.html"
        },
        {
          "name": "sendvid | HD",
          "embed_url": "https://animelek.top/card.php?random=https://sendvid.com/embed/joorezmg"
        },
        {
          "name": "ok ru | FHD",
          "embed_url": "https://animelek.top/card.php?random=https://www.ok.ru/videoembed/6921087552218"
        },
        {
          "name": "mp4upload | FHD",
          "embed_url": "https://animelek.top/card.php?random=https://www.mp4upload.com/embed-y7ctilik01kv.html"
        },
        {
          "name": "mega | FHD",
          "embed_url": "https://animelek.top/card.php?random=https://mega.nz/embed/1CVECYLb!mdAit6x7uYaleZgzsKGbKa1TIzorg2ixhuV5SRhXZh8"
        },
        {
          "name": "ok ru | SD",
          "embed_url": "https://animelek.top/card.php?random=https://www.ok.ru/videoembed/6921107868378"
        },
        {
          "name": "mp4upload | SD",
          "embed_url": "https://animelek.top/card.php?random=https://www.mp4upload.com/embed-9koerdbcxbwg.html"
        },
        {
          "name": "mega | SD",
          "embed_url": "https://animelek.top/card.php?random=https://mega.nz/embed/8TMlQYwA!3lSS-OEFD7aq9avnsWDWe9vM4El0qiBM5ma0tv0dHA8"
        }
      ],
      "downloads": [
        {
          "server": "file-upload",
          "quality": "480p",
          "language": "مترجم",
          "url": "https://www.file-upload.org/5n153m8ryvty"
        },
        {
          "server": "mp4upload",
          "quality": "480p",
          "language": "مترجم",
          "url": "https://www.mp4upload.com/9koerdbcxbwg"
        },
        {
          "server": "mega",
          "quality": "480p",
          "language": "مترجم",
          "url": "https://mega.nz/#!8TMlQYwA!3lSS-OEFD7aq9avnsWDWe9vM4El0qiBM5ma0tv0dHA8"
        },
        {
          "server": "uupbom",
          "quality": "480p",
          "language": "مترجم",
          "url": "http://uupbom.com/wgfq5u4iqawq"
        },
        {
          "server": "updown",
          "quality": "480p",
          "language": "مترجم",
          "url": "https://updown.cam/w6so1w589l0w"
        },
        {
          "server": "mp4upload",
          "quality": "720p",
          "language": "مترجم",
          "url": "https://www.mp4upload.com/ohqi8xw7qo5f"
        },
        {
          "server": "file-upload",
          "quality": "720p",
          "language": "مترجم",
          "url": "https://www.file-upload.org/banekctlkjvm"
        },
        {
          "server": "uupbom",
          "quality": "720p",
          "language": "مترجم",
          "url": "http://uupbom.com/ubuw8od4wvqk"
        },
        {
          "server": "updown",
          "quality": "720p",
          "language": "مترجم",
          "url": "https://updown.cam/f44ov3m0plxf"
        },
        {
          "server": "file-upload",
          "quality": "1080p",
          "language": "مترجم",
          "url": "https://www.file-upload.org/y632689pku8l"
        },
        {
          "server": "mp4upload",
          "quality": "1080p",
          "language": "مترجم",
          "url": "https://www.mp4upload.com/y7ctilik01kv"
        },
        {
          "server": "mega",
          "quality": "1080p",
          "language": "مترجم",
          "url": "https://mega.nz/#!1CVECYLb!mdAit6x7uYaleZgzsKGbKa1TIzorg2ixhuV5SRhXZh8"
        },
        {
          "server": "uupbom",
          "quality": "1080p",
          "language": "مترجم",
          "url": "http://uupbom.com/to14i3vt71up"
        },
        {
          "server": "updown",
          "quality": "1080p",
          "language": "مترجم",
          "url": "https://updown.cam/w1300uvjq3oj"
        }
      ]
    },
    {
      "number": "7",
      "title": "الحلقة 7Seiyuu Radio no Uraomote",
      "date": "22 يونيو, 2024",
      "servers": [
        {
          "name": "megamax me | HD",
          "embed_url": "https://animelek.top/card.php?random=https://megamax.me/iframe/sR9GgoGDpcSun"
        },
        {
          "name": "leech megamax | HD",
          "embed_url": "https://animelek.top/card.php?random=https://leech.megamax.me/e/sR9GgoGDpcSun"
        },
        {
          "name": "megamax me | HD",
          "embed_url": "https://animelek.top/card.php?random=https://megamax.me/iframe/sR9GgoGDpcSun"
        },
        {
          "name": "segavid | HD",
          "embed_url": "https://animelek.top/card.php?random=https://segavid.com/embed-pfq79taua3xq.html"
        },
        {
          "name": "vidmoly to | HD",
          "embed_url": "https://animelek.top/card.php?random=//vidmoly.to/embed-d967e9gvx5ql.html"
        },
        {
          "name": "ok ru | HD",
          "embed_url": "https://animelek.top/card.php?random=https://www.ok.ru/videoembed/6944874105562"
        },
        {
          "name": "mp4upload | HD",
          "embed_url": "https://animelek.top/card.php?random=https://www.mp4upload.com/embed-c3ojmka1hwwu.html"
        },
        {
          "name": "mega | HD",
          "embed_url": "https://animelek.top/card.php?random=https://mega.nz/embed/zP5wBA4I!4aKr0Dof5NUA16zJLYO6uH5enc3NxjolAYBEwg6lask"
        },
        {
          "name": "sendvid | HD",
          "embed_url": "https://animelek.top/card.php?random=https://sendvid.com/embed/ok65vglr"
        },
        {
          "name": "ok ru | FHD",
          "embed_url": "https://animelek.top/card.php?random=https://www.ok.ru/videoembed/6944868666074"
        },
        {
          "name": "mp4upload | FHD",
          "embed_url": "https://animelek.top/card.php?random=https://www.mp4upload.com/embed-t8zc9k0k3rq2.html"
        },
        {
          "name": "mega | FHD",
          "embed_url": "https://animelek.top/card.php?random=https://mega.nz/embed/2GQDwI7a!4WrDp2qJzb7puJbAcgTn-OJSYRsRHXPeEyuWX8RXItU"
        },
        {
          "name": "ok ru | SD",
          "embed_url": "https://animelek.top/card.php?random=https://www.ok.ru/videoembed/6944877578970"
        },
        {
          "name": "mp4upload | SD",
          "embed_url": "https://animelek.top/card.php?random=https://www.mp4upload.com/embed-5vovvlfaue7x.html"
        },
        {
          "name": "mega | SD",
          "embed_url": "https://animelek.top/card.php?random=https://mega.nz/embed/LDZGwSpa!-lQb22vQQWwIiiHsz_pCLDe9hvV3-CjpmOKa1rTujQI"
        }
      ],
      "downloads": [
        {
          "server": "mp4upload",
          "quality": "480p",
          "language": "مترجم",
          "url": "https://www.mp4upload.com/5vovvlfaue7x"
        },
        {
          "server": "file-upload",
          "quality": "480p",
          "language": "مترجم",
          "url": "https://www.file-upload.org/rwixg8egpovd"
        },
        {
          "server": "mega",
          "quality": "480p",
          "language": "مترجم",
          "url": "https://mega.nz/#!LDZGwSpa!-lQb22vQQWwIiiHsz_pCLDe9hvV3-CjpmOKa1rTujQI"
        },
        {
          "server": "uupbom",
          "quality": "480p",
          "language": "مترجم",
          "url": "http://uupbom.com/sjud6kz9acoh"
        },
        {
          "server": "updown",
          "quality": "480p",
          "language": "مترجم",
          "url": "https://updown.cam/5jcumy6jj7fo"
        },
        {
          "server": "file-upload",
          "quality": "720p",
          "language": "مترجم",
          "url": "https://www.file-upload.org/c3nygulc53is"
        },
        {
          "server": "mp4upload",
          "quality": "720p",
          "language": "مترجم",
          "url": "https://www.mp4upload.com/c3ojmka1hwwu"
        },
        {
          "server": "mega",
          "quality": "720p",
          "language": "مترجم",
          "url": "https://mega.nz/#!zP5wBA4I!4aKr0Dof5NUA16zJLYO6uH5enc3NxjolAYBEwg6lask"
        },
        {
          "server": "uupbom",
          "quality": "720p",
          "language": "مترجم",
          "url": "http://uupbom.com/1jo05mfj2kol"
        },
        {
          "server": "updown",
          "quality": "720p",
          "language": "مترجم",
          "url": "https://updown.cam/r5hx1qiv2dre"
        },
        {
          "server": "file-upload",
          "quality": "1080p",
          "language": "مترجم",
          "url": "https://www.file-upload.org/gz6sefzn139r"
        },
        {
          "server": "mp4upload",
          "quality": "1080p",
          "language": "مترجم",
          "url": "https://www.mp4upload.com/t8zc9k0k3rq2"
        },
        {
          "server": "mega",
          "quality": "1080p",
          "language": "مترجم",
          "url": "https://mega.nz/#!2GQDwI7a!4WrDp2qJzb7puJbAcgTn-OJSYRsRHXPeEyuWX8RXItU"
        },
        {
          "server": "uupbom",
          "quality": "1080p",
          "language": "مترجم",
          "url": "http://uupbom.com/pfcvi9sasphr"
        },
        {
          "server": "updown",
          "quality": "1080p",
          "language": "مترجم",
          "url": "https://updown.cam/9cci82furxsg"
        }
      ]
    },
    {
      "number": "5",
      "title": "الحلقة 5Seiyuu Radio no Uraomote",
      "date": "22 يونيو, 2024",
      "servers": [
        {
          "name": "megamax me | HD",
          "embed_url": "https://animelek.top/card.php?random=https://megamax.me/iframe/6roh9gev1iJGJ"
        },
        {
          "name": "leech megamax | HD",
          "embed_url": "https://animelek.top/card.php?random=https://leech.megamax.me/e/6roh9gev1iJGJ"
        },
        {
          "name": "megamax me | HD",
          "embed_url": "https://animelek.top/card.php?random=https://megamax.me/iframe/6roh9gev1iJGJ"
        },
        {
          "name": "segavid | HD",
          "embed_url": "https://animelek.top/card.php?random=https://segavid.com/embed-g0kecfyl5hlr.html"
        },
        {
          "name": "vidmoly to | HD",
          "embed_url": "https://animelek.top/card.php?random=//vidmoly.to/embed-ewmv264rmo3y.html"
        },
        {
          "name": "uqload to | HD",
          "embed_url": "https://animelek.top/card.php?random=https://uqload.to/embed-c84f16qld53i.html"
        },
        {
          "name": "ok ru | HD",
          "embed_url": "https://animelek.top/card.php?random=https://www.ok.ru/videoembed/6901223525082"
        },
        {
          "name": "mp4upload | HD",
          "embed_url": "https://animelek.top/card.php?random=https://www.mp4upload.com/embed-kc4fkfbvg6hg.html"
        },
        {
          "name": "mega | HD",
          "embed_url": "https://animelek.top/card.php?random=https://mega.nz/embed/1DMSwIqD!4uZJKyzTTW2hS4q7E6lU7faOkFdr8xxc6Rrq4yrahaM"
        },
        {
          "name": "sendvid | HD",
          "embed_url": "https://animelek.top/card.php?random=https://sendvid.com/embed/oshkuve3"
        },
        {
          "name": "ok ru | FHD",
          "embed_url": "https://animelek.top/card.php?random=https://www.ok.ru/videoembed/6901212318426"
        },
        {
          "name": "mp4upload | FHD",
          "embed_url": "https://animelek.top/card.php?random=https://www.mp4upload.com/embed-tibh4a0kdbir.html"
        },
        {
          "name": "mega | FHD",
          "embed_url": "https://animelek.top/card.php?random=https://mega.nz/embed/VDswBSSB!PswyP0IcTSZxYPHN-so9bkUkd-e46LVViyUFJx_v1RU"
        },
        {
          "name": "ok ru | SD",
          "embed_url": "https://animelek.top/card.php?random=https://www.ok.ru/videoembed/6901235714778"
        },
        {
          "name": "mp4upload | SD",
          "embed_url": "https://animelek.top/card.php?random=https://www.mp4upload.com/embed-5svf1ljxsnr5.html"
        },
        {
          "name": "mega | SD",
          "embed_url": "https://animelek.top/card.php?random=https://mega.nz/embed/sX8jXBIQ!viL-KVURdlMAAOOplUp-UAE2Ks1NSfFT0WB5bHZEHbk"
        }
      ],
      "downloads": [
        {
          "server": "mp4upload",
          "quality": "480p",
          "language": "مترجم",
          "url": "https://www.mp4upload.com/5svf1ljxsnr5"
        },
        {
          "server": "file-upload",
          "quality": "480p",
          "language": "مترجم",
          "url": "https://www.file-upload.org/54ilft02d0nr"
        },
        {
          "server": "mega",
          "quality": "480p",
          "language": "مترجم",
          "url": "https://mega.nz/#!sX8jXBIQ!viL-KVURdlMAAOOplUp-UAE2Ks1NSfFT0WB5bHZEHbk"
        },
        {
          "server": "uupbom",
          "quality": "480p",
          "language": "مترجم",
          "url": "http://uupbom.com/a8egk9fm4cw4"
        },
        {
          "server": "mp4upload",
          "quality": "720p",
          "language": "مترجم",
          "url": "https://www.mp4upload.com/kc4fkfbvg6hg"
        },
        {
          "server": "file-upload",
          "quality": "720p",
          "language": "مترجم",
          "url": "https://www.file-upload.org/vdtmzyk9rizz"
        },
        {
          "server": "mega",
          "quality": "720p",
          "language": "مترجم",
          "url": "https://mega.nz/#!1DMSwIqD!4uZJKyzTTW2hS4q7E6lU7faOkFdr8xxc6Rrq4yrahaM"
        },
        {
          "server": "uupbom",
          "quality": "720p",
          "language": "مترجم",
          "url": "http://uupbom.com/phckeejeulr1"
        },
        {
          "server": "mp4upload",
          "quality": "1080p",
          "language": "مترجم",
          "url": "https://www.mp4upload.com/tibh4a0kdbir"
        },
        {
          "server": "file-upload",
          "quality": "1080p",
          "language": "مترجم",
          "url": "https://www.file-upload.org/k8tg1hg93dyd"
        },
        {
          "server": "mega",
          "quality": "1080p",
          "language": "مترجم",
          "url": "https://mega.nz/#!VDswBSSB!PswyP0IcTSZxYPHN-so9bkUkd-e46LVViyUFJx_v1RU"
        },
        {
          "server": "uupbom",
          "quality": "1080p",
          "language": "مترجم",
          "url": "http://uupbom.com/t6mbhvtxkmu9"
        }
      ]
    },
    {
      "number": "3",
      "title": "الحلقة 3Seiyuu Radio no Uraomote",
      "date": "22 يونيو, 2024",
      "servers": [
        {
          "name": "megamax me | HD",
          "embed_url": "https://animelek.top/card.php?random=https://megamax.me/iframe/zB0CAC3OoU0bg"
        },
        {
          "name": "leech megamax | HD",
          "embed_url": "https://animelek.top/card.php?random=https://leech.megamax.me/e/zB0CAC3OoU0bg"
        },
        {
          "name": "megamax me | HD",
          "embed_url": "https://animelek.top/card.php?random=https://megamax.me/iframe/zB0CAC3OoU0bg"
        },
        {
          "name": "vidmoly to | HD",
          "embed_url": "https://animelek.top/card.php?random=//vidmoly.to/embed-34txqhkdhwqu.html"
        },
        {
          "name": "uqload to | HD",
          "embed_url": "https://animelek.top/card.php?random=https://uqload.to/embed-bl6awn4v3a3c.html"
        },
        {
          "name": "ok ru | HD",
          "embed_url": "https://animelek.top/card.php?random=https://www.ok.ru/videoembed/6855946537690"
        },
        {
          "name": "mp4upload | HD",
          "embed_url": "https://animelek.top/card.php?random=https://www.mp4upload.com/embed-fr7f0cwokn3l.html"
        },
        {
          "name": "mega | HD",
          "embed_url": "https://animelek.top/card.php?random=https://mega.nz/embed/dBIhjD5A!b6C8GvSaloIptScvtdD0Wlhk-aFf8mdyotktCUzXAq8"
        },
        {
          "name": "sendvid | HD",
          "embed_url": "https://animelek.top/card.php?random=https://sendvid.com/embed/xmw4wvun"
        },
        {
          "name": "ok ru | FHD",
          "embed_url": "https://animelek.top/card.php?random=https://www.ok.ru/videoembed/6855941425882"
        },
        {
          "name": "mp4upload | FHD",
          "embed_url": "https://animelek.top/card.php?random=https://www.mp4upload.com/embed-5s003ivu4v31.html"
        },
        {
          "name": "mega | FHD",
          "embed_url": "https://animelek.top/card.php?random=https://mega.nz/embed/tI5A1SJb!ZMg8AcqLcKT36T4R8jSlAhlxbALx17YzgmsLalKnASQ"
        },
        {
          "name": "ok ru | SD",
          "embed_url": "https://animelek.top/card.php?random=https://www.ok.ru/videoembed/6855951649498"
        },
        {
          "name": "mp4upload | SD",
          "embed_url": "https://animelek.top/card.php?random=https://www.mp4upload.com/embed-ewvmvbr7xiqr.html"
        },
        {
          "name": "mega | SD",
          "embed_url": "https://animelek.top/card.php?random=https://mega.nz/embed/5ERHUTKQ!yZhaUFo1Ey0XZROBRDm3Zqe74CDzPDyi8JU7hURRVF0"
        }
      ],
      "downloads": [
        {
          "server": "mp4upload",
          "quality": "480p",
          "language": "مترجم",
          "url": "https://www.mp4upload.com/ewvmvbr7xiqr"
        },
        {
          "server": "file-upload",
          "quality": "480p",
          "language": "مترجم",
          "url": "https://www.file-upload.org/0zo1lu33nyqt"
        },
        {
          "server": "mega",
          "quality": "480p",
          "language": "مترجم",
          "url": "https://mega.nz/#!5ERHUTKQ!yZhaUFo1Ey0XZROBRDm3Zqe74CDzPDyi8JU7hURRVF0"
        },
        {
          "server": "uupbom",
          "quality": "480p",
          "language": "مترجم",
          "url": "http://uupbom.com/qxqihauz8dr6"
        },
        {
          "server": "mp4upload",
          "quality": "720p",
          "language": "مترجم",
          "url": "https://www.mp4upload.com/fr7f0cwokn3l"
        },
        {
          "server": "file-upload",
          "quality": "720p",
          "language": "مترجم",
          "url": "https://www.file-upload.org/qkbik3b2h3rl"
        },
        {
          "server": "mega",
          "quality": "720p",
          "language": "مترجم",
          "url": "https://mega.nz/#!dBIhjD5A!b6C8GvSaloIptScvtdD0Wlhk-aFf8mdyotktCUzXAq8"
        },
        {
          "server": "uupbom",
          "quality": "720p",
          "language": "مترجم",
          "url": "http://uupbom.com/45cn57xi3e8x"
        },
        {
          "server": "file-upload",
          "quality": "1080p",
          "language": "مترجم",
          "url": "https://www.file-upload.org/2vwfihaz7a5a"
        },
        {
          "server": "mp4upload",
          "quality": "1080p",
          "language": "مترجم",
          "url": "https://www.mp4upload.com/5s003ivu4v31"
        },
        {
          "server": "mega",
          "quality": "1080p",
          "language": "مترجم",
          "url": "https://mega.nz/#!tI5A1SJb!ZMg8AcqLcKT36T4R8jSlAhlxbALx17YzgmsLalKnASQ"
        },
        {
          "server": "uupbom",
          "quality": "1080p",
          "language": "مترجم",
          "url": "http://uupbom.com/rlc0xwmlq2fn"
        }
      ]
    },
    {
      "number": "4",
      "title": "الحلقة 4Seiyuu Radio no Uraomote",
      "date": "22 يونيو, 2024",
      "servers": [
        {
          "name": "megamax me | HD",
          "embed_url": "https://animelek.top/card.php?random=https://megamax.me/iframe/kP8jmx8DCnDkJ"
        },
        {
          "name": "leech megamax | HD",
          "embed_url": "https://animelek.top/card.php?random=https://leech.megamax.me/e/kP8jmx8DCnDkJ"
        },
        {
          "name": "megamax me | HD",
          "embed_url": "https://animelek.top/card.php?random=https://megamax.me/iframe/kP8jmx8DCnDkJ"
        },
        {
          "name": "segavid | HD",
          "embed_url": "https://animelek.top/card.php?random=https://segavid.com/embed-8y0emlniy7rg.html"
        },
        {
          "name": "vidmoly to | HD",
          "embed_url": "https://animelek.top/card.php?random=//vidmoly.to/embed-fqte59bu3feh.html"
        },
        {
          "name": "uqload to | HD",
          "embed_url": "https://animelek.top/card.php?random=https://uqload.to/embed-44cfqhs78vew.html"
        },
        {
          "name": "ok ru | HD",
          "embed_url": "https://animelek.top/card.php?random=https://www.ok.ru/videoembed/6879964957402"
        },
        {
          "name": "mp4upload | HD",
          "embed_url": "https://animelek.top/card.php?random=https://www.mp4upload.com/embed-3pf865ijjo8z.html"
        },
        {
          "name": "mega | HD",
          "embed_url": "https://animelek.top/card.php?random=https://mega.nz/embed/tf1RgQrL!NFwEsT-o2j1Hhz3WeuMapDyE959Z2t7TEFt6Tm8_C08"
        },
        {
          "name": "sendvid | HD",
          "embed_url": "https://animelek.top/card.php?random=https://sendvid.com/embed/b6lsrw4r"
        },
        {
          "name": "ok ru | FHD",
          "embed_url": "https://animelek.top/card.php?random=https://www.ok.ru/videoembed/6879958272730"
        },
        {
          "name": "mp4upload | FHD",
          "embed_url": "https://animelek.top/card.php?random=https://www.mp4upload.com/embed-zw51g40sfb2w.html"
        },
        {
          "name": "mega | FHD",
          "embed_url": "https://animelek.top/card.php?random=https://mega.nz/embed/VX1G0TxQ!-FwxANjYfHyKObTZ_k_HiEHxmfCh_FvxLFghZXhcSeY"
        },
        {
          "name": "ok ru | SD",
          "embed_url": "https://animelek.top/card.php?random=https://www.ok.ru/videoembed/6879969020634"
        },
        {
          "name": "mp4upload | SD",
          "embed_url": "https://animelek.top/card.php?random=https://www.mp4upload.com/embed-7ghc9i8xar3c.html"
        },
        {
          "name": "mega | SD",
          "embed_url": "https://animelek.top/card.php?random=https://mega.nz/embed/pSdm3TDA!9kKV7fZ99yyVY5e3u4qPLll0m4wI3jmJzqvLaHvxZjg"
        }
      ],
      "downloads": [
        {
          "server": "file-upload",
          "quality": "480p",
          "language": "مترجم",
          "url": "https://www.file-upload.org/7nvkbzl8en42"
        },
        {
          "server": "mp4upload",
          "quality": "480p",
          "language": "مترجم",
          "url": "https://www.mp4upload.com/7ghc9i8xar3c"
        },
        {
          "server": "mega",
          "quality": "480p",
          "language": "مترجم",
          "url": "https://mega.nz/#!pSdm3TDA!9kKV7fZ99yyVY5e3u4qPLll0m4wI3jmJzqvLaHvxZjg"
        },
        {
          "server": "uupbom",
          "quality": "480p",
          "language": "مترجم",
          "url": "http://uupbom.com/1c63m93c75o2"
        },
        {
          "server": "mp4upload",
          "quality": "720p",
          "language": "مترجم",
          "url": "https://www.mp4upload.com/3pf865ijjo8z"
        },
        {
          "server": "file-upload",
          "quality": "720p",
          "language": "مترجم",
          "url": "https://www.file-upload.org/400ym72mabad"
        },
        {
          "server": "mega",
          "quality": "720p",
          "language": "مترجم",
          "url": "https://mega.nz/#!tf1RgQrL!NFwEsT-o2j1Hhz3WeuMapDyE959Z2t7TEFt6Tm8_C08"
        },
        {
          "server": "uupbom",
          "quality": "720p",
          "language": "مترجم",
          "url": "http://uupbom.com/wf2e0k8abouc"
        },
        {
          "server": "mp4upload",
          "quality": "1080p",
          "language": "مترجم",
          "url": "https://www.mp4upload.com/zw51g40sfb2w"
        },
        {
          "server": "file-upload",
          "quality": "1080p",
          "language": "مترجم",
          "url": "https://www.file-upload.org/ub1cm551eoe8"
        },
        {
          "server": "mega",
          "quality": "1080p",
          "language": "مترجم",
          "url": "https://mega.nz/#!VX1G0TxQ!-FwxANjYfHyKObTZ_k_HiEHxmfCh_FvxLFghZXhcSeY"
        },
        {
          "server": "uupbom",
          "quality": "1080p",
          "language": "مترجم",
          "url": "http://uupbom.com/p2axhke8qmdq"
        }
      ]
    },
    {
      "number": "2",
      "title": "الحلقة 2Seiyuu Radio no Uraomote",
      "date": "22 يونيو, 2024",
      "servers": [
        {
          "name": "megamax me | HD",
          "embed_url": "https://animelek.top/card.php?random=https://megamax.me/iframe/AgKcBBXorrTVP"
        },
        {
          "name": "leech megamax | HD",
          "embed_url": "https://animelek.top/card.php?random=https://leech.megamax.me/e/AgKcBBXorrTVP"
        },
        {
          "name": "megamax me | HD",
          "embed_url": "https://animelek.top/card.php?random=https://megamax.me/iframe/AgKcBBXorrTVP"
        },
        {
          "name": "vidmoly to | HD",
          "embed_url": "https://animelek.top/card.php?random=//vidmoly.to/embed-w7jv7ngv7e0r.html"
        },
        {
          "name": "uqload to | HD",
          "embed_url": "https://animelek.top/card.php?random=https://uqload.to/embed-v06ibyg95d9u.html"
        },
        {
          "name": "ok ru | HD",
          "embed_url": "https://animelek.top/card.php?random=https://www.ok.ru/videoembed/6836220857050"
        },
        {
          "name": "mp4upload | HD",
          "embed_url": "https://animelek.top/card.php?random=https://www.mp4upload.com/embed-nvmz730z50r5.html"
        },
        {
          "name": "mega | HD",
          "embed_url": "https://animelek.top/card.php?random=https://mega.nz/embed/dW9VDazC!Ypemw69ZuIN33XO-NSlm2W68AeAdE-cIFXgS_WQ7wGE"
        },
        {
          "name": "sendvid | HD",
          "embed_url": "https://animelek.top/card.php?random=https://sendvid.com/embed/628c2c4z"
        },
        {
          "name": "ok ru | FHD",
          "embed_url": "https://animelek.top/card.php?random=https://www.ok.ru/videoembed/6836216138458"
        },
        {
          "name": "mp4upload | FHD",
          "embed_url": "https://animelek.top/card.php?random=https://www.mp4upload.com/embed-579mi7so59zm.html"
        },
        {
          "name": "mega | FHD",
          "embed_url": "https://animelek.top/card.php?random=https://mega.nz/embed/xSVEAK5R!mvRZxApBrS_5igBI7zi6sxkOQBHt3lnl1j7LLshduxI"
        },
        {
          "name": "ok ru | SD",
          "embed_url": "https://animelek.top/card.php?random=https://www.ok.ru/videoembed/6836227082970"
        },
        {
          "name": "mp4upload | SD",
          "embed_url": "https://animelek.top/card.php?random=https://www.mp4upload.com/embed-rumyetfzr4zy.html"
        },
        {
          "name": "mega | SD",
          "embed_url": "https://animelek.top/card.php?random=https://mega.nz/embed/of9zhSLL!UIlFyss7pr9baKW4RQwGO2J5RELTsKM0pGOIwLhYNDA"
        }
      ],
      "downloads": [
        {
          "server": "mp4upload",
          "quality": "480p",
          "language": "مترجم",
          "url": "https://www.mp4upload.com/rumyetfzr4zy"
        },
        {
          "server": "file-upload",
          "quality": "480p",
          "language": "مترجم",
          "url": "https://www.file-upload.org/6evzypydzzyn"
        },
        {
          "server": "mega",
          "quality": "480p",
          "language": "مترجم",
          "url": "https://mega.nz/#!of9zhSLL!UIlFyss7pr9baKW4RQwGO2J5RELTsKM0pGOIwLhYNDA"
        },
        {
          "server": "uupbom",
          "quality": "480p",
          "language": "مترجم",
          "url": "http://uupbom.com/e0yzavn8hcox"
        },
        {
          "server": "updown",
          "quality": "480p",
          "language": "مترجم",
          "url": "https://updown.cam/3adtafr221vw"
        },
        {
          "server": "mp4upload",
          "quality": "720p",
          "language": "مترجم",
          "url": "https://www.mp4upload.com/nvmz730z50r5"
        },
        {
          "server": "file-upload",
          "quality": "720p",
          "language": "مترجم",
          "url": "https://www.file-upload.org/via206bxesdh"
        },
        {
          "server": "mega",
          "quality": "720p",
          "language": "مترجم",
          "url": "https://mega.nz/#!dW9VDazC!Ypemw69ZuIN33XO-NSlm2W68AeAdE-cIFXgS_WQ7wGE"
        },
        {
          "server": "uupbom",
          "quality": "720p",
          "language": "مترجم",
          "url": "http://uupbom.com/cx5bjjarfp6r"
        },
        {
          "server": "updown",
          "quality": "720p",
          "language": "مترجم",
          "url": "https://updown.cam/pei742qoq4jc"
        },
        {
          "server": "file-upload",
          "quality": "1080p",
          "language": "مترجم",
          "url": "https://www.file-upload.org/puq2wh77ipx4"
        },
        {
          "server": "mp4upload",
          "quality": "1080p",
          "language": "مترجم",
          "url": "https://www.mp4upload.com/579mi7so59zm"
        },
        {
          "server": "mega",
          "quality": "1080p",
          "language": "مترجم",
          "url": "https://mega.nz/#!xSVEAK5R!mvRZxApBrS_5igBI7zi6sxkOQBHt3lnl1j7LLshduxI"
        },
        {
          "server": "uupbom",
          "quality": "1080p",
          "language": "مترجم",
          "url": "http://uupbom.com/inz5zq3k4xt4"
        },
        {
          "server": "updown",
          "quality": "1080p",
          "language": "مترجم",
          "url": "https://updown.cam/bsnm6m131374"
        }
      ]
    },
    {
      "number": "1",
      "title": "الحلقة 1Seiyuu Radio no Uraomote",
      "date": "22 يونيو, 2024",
      "servers": [
        {
          "name": "megamax me | HD",
          "embed_url": "https://animelek.top/card.php?random=https://megamax.me/iframe/Gadf1f9Oh0vIr"
        },
        {
          "name": "leech megamax | HD",
          "embed_url": "https://animelek.top/card.php?random=https://leech.megamax.me/e/Gadf1f9Oh0vIr"
        },
        {
          "name": "megamax me | HD",
          "embed_url": "https://animelek.top/card.php?random=https://megamax.me/iframe/Gadf1f9Oh0vIr"
        },
        {
          "name": "vidmoly to | HD",
          "embed_url": "https://animelek.top/card.php?random=//vidmoly.to/embed-je9hxr62hw5h.html"
        },
        {
          "name": "uqload to | HD",
          "embed_url": "https://animelek.top/card.php?random=https://uqload.to/embed-fc7r2vx0pl6g.html"
        },
        {
          "name": "ok ru | HD",
          "embed_url": "https://animelek.top/card.php?random=https://www.ok.ru/videoembed/6814756571866"
        },
        {
          "name": "mega | HD",
          "embed_url": "https://animelek.top/card.php?random=https://mega.nz/embed/ZvdkEJZb!KD-frd0qo6cqUce7hInA958wlsUriVDSn88aRWI3Dtw"
        },
        {
          "name": "sendvid | HD",
          "embed_url": "https://animelek.top/card.php?random=https://sendvid.com/embed/x6w9u3b1"
        },
        {
          "name": "ok ru | FHD",
          "embed_url": "https://animelek.top/card.php?random=https://www.ok.ru/videoembed/6814738680538"
        },
        {
          "name": "mega | FHD",
          "embed_url": "https://animelek.top/card.php?random=https://mega.nz/embed/hr1DmQxB!moj0FjDbkNaUXLbYKDIJRIP3SxLvH_9dQxt5J1Uuo6A"
        },
        {
          "name": "ok ru | SD",
          "embed_url": "https://animelek.top/card.php?random=https://www.ok.ru/videoembed/6814772366042"
        },
        {
          "name": "mega | SD",
          "embed_url": "https://animelek.top/card.php?random=https://mega.nz/embed/cr9CCZiR!lxrDCUDqiR0PhYdZpb8zRBtCbD0UlwmM1tCK3Yhrc6o"
        }
      ],
      "downloads": [
        {
          "server": "file-upload",
          "quality": "480p",
          "language": "مترجم",
          "url": "https://www.file-upload.org/vo65swt7u4ku"
        },
        {
          "server": "mega",
          "quality": "480p",
          "language": "مترجم",
          "url": "https://mega.nz/#!cr9CCZiR!lxrDCUDqiR0PhYdZpb8zRBtCbD0UlwmM1tCK3Yhrc6o"
        },
        {
          "server": "uupbom",
          "quality": "480p",
          "language": "مترجم",
          "url": "http://uupbom.com/no818afgi9qq"
        },
        {
          "server": "updown",
          "quality": "480p",
          "language": "مترجم",
          "url": "https://updown.cam/9c7effiv6b9u"
        },
        {
          "server": "file-upload",
          "quality": "720p",
          "language": "مترجم",
          "url": "https://www.file-upload.org/zc5v1whl5rnt"
        },
        {
          "server": "mega",
          "quality": "720p",
          "language": "مترجم",
          "url": "https://mega.nz/#!ZvdkEJZb!KD-frd0qo6cqUce7hInA958wlsUriVDSn88aRWI3Dtw"
        },
        {
          "server": "uupbom",
          "quality": "720p",
          "language": "مترجم",
          "url": "http://uupbom.com/y9nqnme1jul4"
        },
        {
          "server": "updown",
          "quality": "720p",
          "language": "مترجم",
          "url": "https://updown.cam/avf4zascfpoi"
        },
        {
          "server": "file-upload",
          "quality": "1080p",
          "language": "مترجم",
          "url": "https://www.file-upload.org/al85ppyyzuo3"
        },
        {
          "server": "mega",
          "quality": "1080p",
          "language": "مترجم",
          "url": "https://mega.nz/#!hr1DmQxB!moj0FjDbkNaUXLbYKDIJRIP3SxLvH_9dQxt5J1Uuo6A"
        },
        {
          "server": "uupbom",
          "quality": "1080p",
          "language": "مترجم",
          "url": "http://uupbom.com/xvel7nvqa1v6"
        },
        {
          "server": "updown",
          "quality": "1080p",
          "language": "مترجم",
          "url": "https://updown.cam/h3112lxx0q74"
        }
      ]
    }
  ],
  "last_updated": "2026-06-25T04:57:21.110642"
}