{
  "id": "zashiki-warashi-no-tatami-chan",
  "title": "انمي Zashiki Warashi no Tatami-chan مترجم اون لاين",
  "url": "https://animelek.top/anime/zashiki-warashi-no-tatami-chan/",
  "poster": "data/posters/zashiki-warashi-no-tatami-chan.webp",
  "status": "مكتمل",
  "type": "أونا",
  "episodes_count": "12",
  "start_date": "2020",
  "season": "ربيع 2020",
  "genres": [
    "كوميدي",
    "قوى خارقة",
    "رعب"
  ],
  "story": "قصة انمي Zashiki Warashi no Tatami-chan تحدث عن روح ربة منزل تنتقل من إحدى البلدان في اليابان، إلى العاصمة المزدحمة طوكيو، حيث المعيشة هناك تكون صعبة حتى على الأرواح غير البشرية. وبما أن هذا المجتمع عجيب، الغرابة لم تأتِ بعد يا رفاق. عندما ذهبت الروح إلى طوكيو، وجدت منزلها خاليًا من الكهرباء والغاز الطبيعي وكل شيء تقريبًا، ولذلك قررت أن تُسكن معها روح وحش (يوكاي)، وفتاة بشرية. ومن هنا تبدأ الكوميديا الإرعابية الفريدة من نوعها.",
  "episodes": [
    {
      "number": "11",
      "title": "الأونا 11Zashiki Warashi no Tatami-chan",
      "date": "15 يوليو, 2020",
      "servers": [
        {
          "name": "4shared | HD",
          "embed_url": "https://animelek.top/card.php?random=https://www.4shared.com/web/embed/file/XB32hAIliq"
        },
        {
          "name": "ok ru | HD",
          "embed_url": "https://animelek.top/card.php?random=https://ok.ru/videoembed/1519874018010"
        },
        {
          "name": "google | HD",
          "embed_url": "https://animelek.top/card.php?random=https://drive.google.com/file/d/10JEd51RJO3IFkSTd5VMf4v3wiwTca7pR/preview"
        },
        {
          "name": "vidbem | HD",
          "embed_url": "https://animelek.top/card.php?random=https://vidbem.com/embed-53pgl4l5yabs.html"
        },
        {
          "name": "vidfast | HD",
          "embed_url": "https://animelek.top/card.php?random=https://vidfast.co/embed-lx1blrs804kx.html"
        },
        {
          "name": "uqload | HD",
          "embed_url": "https://animelek.top/card.php?random=https://uqload.com/embed-stw355e20kty.html"
        },
        {
          "name": "mega | HD",
          "embed_url": "https://animelek.top/card.php?random=https://mega.nz/embed/vZxVFRRD#pR7_IraJxeijKVn9qoQV9HRMAUfeuexKAIo7MgY8-rI"
        },
        {
          "name": "uptostream | HD",
          "embed_url": "https://animelek.top/card.php?random=https://uptostream.com/iframe/86x2869531of"
        },
        {
          "name": "7-up | HD",
          "embed_url": "https://animelek.top/card.php?random=https://7-up.net/embed-oycrbqbnqf77.html"
        },
        {
          "name": "mp4upload | HD",
          "embed_url": "https://animelek.top/card.php?random=https://www.mp4upload.com/embed-xds3d3syrt81.html"
        }
      ],
      "downloads": [
        {
          "server": "file-upload",
          "quality": "720p",
          "language": "مترجم",
          "url": "https://www.file-upload.com/6jhhws5sxw43"
        },
        {
          "server": "drive",
          "quality": "720p",
          "language": "مترجم",
          "url": "https://drive.google.com/u/0/uc?id=10JEd51RJO3IFkSTd5VMf4v3wiwTca7pR&export=download"
        },
        {
          "server": "mega",
          "quality": "720p",
          "language": "مترجم",
          "url": "https://mega.nz/file/vZxVFRRD#pR7_IraJxeijKVn9qoQV9HRMAUfeuexKAIo7MgY8-rI"
        },
        {
          "server": "mp4upload",
          "quality": "720p",
          "language": "مترجم",
          "url": "https://www.mp4upload.com/xds3d3syrt81"
        },
        {
          "server": "7-up",
          "quality": "720p",
          "language": "مترجم",
          "url": "https://7-up.net/oycrbqbnqf77.html"
        },
        {
          "server": "letsupload",
          "quality": "720p",
          "language": "مترجم",
          "url": "https://letsupload.co/mcqM"
        },
        {
          "server": "uptobox",
          "quality": "720p",
          "language": "مترجم",
          "url": "https://uptobox.com/86x2869531of"
        },
        {
          "server": "4shared",
          "quality": "720p",
          "language": "مترجم",
          "url": "https://www.4shared.com/video/XB32hAIliq/Anime4upcom_ZWNTC_EP_11_HD.html"
        }
      ]
    },
    {
      "number": "12",
      "title": "الأونا 12Zashiki Warashi no Tatami-chan",
      "date": "15 يوليو, 2020",
      "servers": [
        {
          "name": "4shared | HD",
          "embed_url": "https://animelek.top/card.php?random=https://www.4shared.com/web/embed/file/yUb69ndjea"
        },
        {
          "name": "ok ru | HD",
          "embed_url": "https://animelek.top/card.php?random=https://ok.ru/videoembed/1519886338778"
        },
        {
          "name": "google | HD",
          "embed_url": "https://animelek.top/card.php?random=https://drive.google.com/file/d/1N5TGRkbOolSwqxPZ23XyevOK3Na_QJHR/preview"
        },
        {
          "name": "vidbem | HD",
          "embed_url": "https://animelek.top/card.php?random=https://vidbem.com/embed-65uvxlp4ya7i.html"
        },
        {
          "name": "vidfast | HD",
          "embed_url": "https://animelek.top/card.php?random=https://vidfast.co/embed-0llzfj7qvnjz.html"
        },
        {
          "name": "uqload | HD",
          "embed_url": "https://animelek.top/card.php?random=https://uqload.com/embed-eal3i2yh064u.html"
        },
        {
          "name": "mega | HD",
          "embed_url": "https://animelek.top/card.php?random=https://mega.nz/embed/XcJA3YZJ#MoTfYeua28e0SVtFLy2L3vXtuLgliSt6HCDPh4uGLeY"
        },
        {
          "name": "uptostream | HD",
          "embed_url": "https://animelek.top/card.php?random=https://uptostream.com/iframe/i8ipjy5n581j"
        },
        {
          "name": "7-up | HD",
          "embed_url": "https://animelek.top/card.php?random=https://7-up.net/embed-qfc0zoourta2.html"
        },
        {
          "name": "mp4upload | HD",
          "embed_url": "https://animelek.top/card.php?random=https://www.mp4upload.com/embed-49opncg90f0u.html"
        }
      ],
      "downloads": [
        {
          "server": "file-upload",
          "quality": "720p",
          "language": "مترجم",
          "url": "https://www.file-upload.com/6oe31gsuwu8o"
        },
        {
          "server": "drive",
          "quality": "720p",
          "language": "مترجم",
          "url": "https://drive.google.com/u/0/uc?id=1N5TGRkbOolSwqxPZ23XyevOK3Na_QJHR&export=download"
        },
        {
          "server": "mega",
          "quality": "720p",
          "language": "مترجم",
          "url": "https://mega.nz/file/XcJA3YZJ#MoTfYeua28e0SVtFLy2L3vXtuLgliSt6HCDPh4uGLeY"
        },
        {
          "server": "mp4upload",
          "quality": "720p",
          "language": "مترجم",
          "url": "https://www.mp4upload.com/49opncg90f0u"
        },
        {
          "server": "7-up",
          "quality": "720p",
          "language": "مترجم",
          "url": "https://7-up.net/qfc0zoourta2.html"
        },
        {
          "server": "letsupload",
          "quality": "720p",
          "language": "مترجم",
          "url": "https://letsupload.co/mcrT"
        },
        {
          "server": "uptobox",
          "quality": "720p",
          "language": "مترجم",
          "url": "https://uptobox.com/i8ipjy5n581j"
        },
        {
          "server": "4shared",
          "quality": "720p",
          "language": "مترجم",
          "url": "https://www.4shared.com/video/yUb69ndjea/Anime4upcom_ZWNTC_EP_12_HD.html"
        }
      ]
    },
    {
      "number": "9",
      "title": "الأونا 9Zashiki Warashi no Tatami-chan",
      "date": "15 يوليو, 2020",
      "servers": [
        {
          "name": "4shared | HD",
          "embed_url": "https://animelek.top/card.php?random=https://www.4shared.com/web/embed/file/GkyLHKl0ea"
        },
        {
          "name": "ok ru | HD",
          "embed_url": "https://animelek.top/card.php?random=https://ok.ru/videoembed/1488756017882"
        },
        {
          "name": "google | HD",
          "embed_url": "https://animelek.top/card.php?random=https://drive.google.com/file/d/1_IfvZug9b1D1pZFzbhrp2LrWfCDLXPln/preview"
        },
        {
          "name": "solidfiles | HD",
          "embed_url": "https://animelek.top/card.php?random=https://www.solidfiles.com/e/vzvZ5Dx5VzdwP"
        },
        {
          "name": "mega | HD",
          "embed_url": "https://animelek.top/card.php?random=https://mega.nz/embed/EAxxmZpQ#-0GU5BWcyqZ-GbTUcSI0XKiW4k7Jp_vY4CrRwtaNHa8"
        },
        {
          "name": "uptostream | HD",
          "embed_url": "https://animelek.top/card.php?random=https://uptostream.com/iframe/u5j3mwqxz0k0"
        },
        {
          "name": "vidbm | HD",
          "embed_url": "https://animelek.top/card.php?random=https://www.vidbm.com/embed-k91rmm6sptnz.html"
        },
        {
          "name": "vidfast | HD",
          "embed_url": "https://animelek.top/card.php?random=https://vidfast.co/embed-z0qfz4nu0149.html"
        },
        {
          "name": "mp4upload | HD",
          "embed_url": "https://animelek.top/card.php?random=https://www.mp4upload.com/embed-09a34iy1xcpn.html"
        }
      ],
      "downloads": [
        {
          "server": "file-upload",
          "quality": "720p",
          "language": "مترجم",
          "url": "https://www.file-upload.com/ng68f05qw5wr"
        },
        {
          "server": "drive",
          "quality": "720p",
          "language": "مترجم",
          "url": "https://drive.google.com/u/0/uc?id=1_IfvZug9b1D1pZFzbhrp2LrWfCDLXPln&export=download"
        },
        {
          "server": "mega",
          "quality": "720p",
          "language": "مترجم",
          "url": "https://mega.nz/file/EAxxmZpQ#-0GU5BWcyqZ-GbTUcSI0XKiW4k7Jp_vY4CrRwtaNHa8"
        },
        {
          "server": "mp4upload",
          "quality": "720p",
          "language": "مترجم",
          "url": "https://www.mp4upload.com/09a34iy1xcpn"
        },
        {
          "server": "uptobox",
          "quality": "720p",
          "language": "مترجم",
          "url": "https://uptobox.com/u5j3mwqxz0k0"
        },
        {
          "server": "solidfiles",
          "quality": "720p",
          "language": "مترجم",
          "url": "https://www.solidfiles.com/v/vzvZ5Dx5VzdwP"
        },
        {
          "server": "4shared",
          "quality": "720p",
          "language": "مترجم",
          "url": "https://www.4shared.com/video/GkyLHKl0ea/Anime4upcom_ZWNTC_EP_09_HD.html"
        }
      ]
    },
    {
      "number": "10",
      "title": "الأونا 10Zashiki Warashi no Tatami-chan",
      "date": "15 يوليو, 2020",
      "servers": [
        {
          "name": "ok ru | HD",
          "embed_url": "https://animelek.top/card.php?random=https://ok.ru/videoembed/1498762775258"
        },
        {
          "name": "google | HD",
          "embed_url": "https://animelek.top/card.php?random=https://drive.google.com/file/d/1o1Bc5JfhccctEhSN6srGTuEmGXUjqbX2/preview"
        },
        {
          "name": "solidfiles | HD",
          "embed_url": "https://animelek.top/card.php?random=https://www.solidfiles.com/e/7GqBkDnLqN352"
        },
        {
          "name": "mega | HD",
          "embed_url": "https://animelek.top/card.php?random=https://mega.nz/embed/ZUhxCRJD#yCBNSd-wOggEVhRCRHTM0L2WagnPY5CxalFWTdDDKJI"
        },
        {
          "name": "vidbm | HD",
          "embed_url": "https://animelek.top/card.php?random=https://www.vidbm.com/embed-n8nnwqu02x4u.html"
        },
        {
          "name": "vidfast | HD",
          "embed_url": "https://animelek.top/card.php?random=https://vidfast.co/embed-ndxpnbqei0si.html"
        },
        {
          "name": "uqload | HD",
          "embed_url": "https://animelek.top/card.php?random=https://uqload.com/embed-9tyyv83g3b9h.html"
        },
        {
          "name": "uptostream | HD",
          "embed_url": "https://animelek.top/card.php?random=https://uptostream.com/iframe/ktx4xxb1xujt"
        },
        {
          "name": "7-up | HD",
          "embed_url": "https://animelek.top/card.php?random=https://7-up.net/embed-t46k778w9izv.html"
        },
        {
          "name": "mp4upload | HD",
          "embed_url": "https://animelek.top/card.php?random=https://www.mp4upload.com/embed-8fbuahfpjy3a.html"
        }
      ],
      "downloads": [
        {
          "server": "file-upload",
          "quality": "720p",
          "language": "مترجم",
          "url": "https://www.file-upload.com/1de38wa5jxwz"
        },
        {
          "server": "drive",
          "quality": "720p",
          "language": "مترجم",
          "url": "https://drive.google.com/u/0/uc?id=1o1Bc5JfhccctEhSN6srGTuEmGXUjqbX2&export=download"
        },
        {
          "server": "mega",
          "quality": "720p",
          "language": "مترجم",
          "url": "https://mega.nz/file/ZUhxCRJD#yCBNSd-wOggEVhRCRHTM0L2WagnPY5CxalFWTdDDKJI"
        },
        {
          "server": "mp4upload",
          "quality": "720p",
          "language": "مترجم",
          "url": "https://www.mp4upload.com/8fbuahfpjy3a"
        },
        {
          "server": "7-up",
          "quality": "720p",
          "language": "مترجم",
          "url": "https://7-up.net/t46k778w9izv.html"
        },
        {
          "server": "uptobox",
          "quality": "720p",
          "language": "مترجم",
          "url": "https://uptobox.com/ktx4xxb1xujt"
        },
        {
          "server": "solidfiles",
          "quality": "720p",
          "language": "مترجم",
          "url": "https://www.solidfiles.com/v/7GqBkDnLqN352"
        }
      ]
    },
    {
      "number": "8",
      "title": "الأونا 8Zashiki Warashi no Tatami-chan",
      "date": "15 يوليو, 2020",
      "servers": [
        {
          "name": "4shared | HD",
          "embed_url": "https://animelek.top/card.php?random=https://www.4shared.com/web/embed/file/Mrl3nsGpea"
        },
        {
          "name": "ok ru | HD",
          "embed_url": "https://animelek.top/card.php?random=https://ok.ru/videoembed/1478141807322"
        },
        {
          "name": "google | HD",
          "embed_url": "https://animelek.top/card.php?random=https://drive.google.com/file/d/1sNlKzU_wl6JqufNT0y9ZucWeQfpblH7e/preview"
        },
        {
          "name": "solidfiles | HD",
          "embed_url": "https://animelek.top/card.php?random=https://www.solidfiles.com/e/Q4W8xVDPKZQ6M"
        },
        {
          "name": "mega | HD",
          "embed_url": "https://animelek.top/card.php?random=https://mega.nz/embed/3JRzWYaT#rOG-m4mTvZg92RHFODdhW_iHWPNxKjAwal_7FMmCEOs"
        },
        {
          "name": "uptostream | HD",
          "embed_url": "https://animelek.top/card.php?random=https://uptostream.com/iframe/0g38jpp9apaa"
        },
        {
          "name": "vidbm | HD",
          "embed_url": "https://animelek.top/card.php?random=https://www.vidbm.com/embed-rpdbmolz2kjg.html"
        },
        {
          "name": "vidfast | HD",
          "embed_url": "https://animelek.top/card.php?random=https://vidfast.co/embed-9nmeffgnwnqr.html"
        },
        {
          "name": "mp4upload | HD",
          "embed_url": "https://animelek.top/card.php?random=https://www.mp4upload.com/embed-4c44k9zkegs2.html"
        },
        {
          "name": "file-upload | HD",
          "embed_url": "https://animelek.top/card.php?random=https://www.file-upload.com/embed-huv6c0xf8bup.html"
        }
      ],
      "downloads": [
        {
          "server": "file-upload",
          "quality": "720p",
          "language": "مترجم",
          "url": "https://www.file-upload.com/huv6c0xf8bup"
        },
        {
          "server": "drive",
          "quality": "720p",
          "language": "مترجم",
          "url": "https://drive.google.com/u/0/uc?id=1sNlKzU_wl6JqufNT0y9ZucWeQfpblH7e&export=download"
        },
        {
          "server": "mega",
          "quality": "720p",
          "language": "مترجم",
          "url": "https://mega.nz/file/3JRzWYaT#rOG-m4mTvZg92RHFODdhW_iHWPNxKjAwal_7FMmCEOs"
        },
        {
          "server": "mp4upload",
          "quality": "720p",
          "language": "مترجم",
          "url": "https://www.mp4upload.com/4c44k9zkegs2"
        },
        {
          "server": "uptobox",
          "quality": "720p",
          "language": "مترجم",
          "url": "https://uptobox.com/0g38jpp9apaa"
        },
        {
          "server": "solidfiles",
          "quality": "720p",
          "language": "مترجم",
          "url": "https://www.solidfiles.com/v/Q4W8xVDPKZQ6M"
        },
        {
          "server": "4shared",
          "quality": "720p",
          "language": "مترجم",
          "url": "https://www.4shared.com/video/Mrl3nsGpea/Anime4upcom_ZWNTC_EP_08_HD.html"
        }
      ]
    },
    {
      "number": "6",
      "title": "الأونا 6Zashiki Warashi no Tatami-chan",
      "date": "15 يوليو, 2020",
      "servers": [
        {
          "name": "ok ru | HD",
          "embed_url": "https://animelek.top/card.php?random=https://ok.ru/videoembed/1459526961882"
        },
        {
          "name": "letsupload | HD",
          "embed_url": "https://animelek.top/card.php?random=https://letsupload.co/plugins/mediaplayer/site/_embed.php?u=3zRTT&w=640&h=320"
        },
        {
          "name": "google | HD",
          "embed_url": "https://animelek.top/card.php?random=https://drive.google.com/file/d/1GDEUwRd5hMFZ3_WRGFbbtn5R0hVCl1Nn/preview"
        },
        {
          "name": "solidfiles | HD",
          "embed_url": "https://animelek.top/card.php?random=https://www.solidfiles.com/e/ABjWBz6Kk482P"
        },
        {
          "name": "mega | HD",
          "embed_url": "https://animelek.top/card.php?random=https://mega.nz/embed/qfIzASYJ#8By8ykPS73ITeZ97zUKtLIBB49EWOb9InrEXvrOhWbU"
        },
        {
          "name": "uptostream | HD",
          "embed_url": "https://animelek.top/card.php?random=https://uptostream.com/iframe/0onnwonvk9zs"
        },
        {
          "name": "vidbm | HD",
          "embed_url": "https://animelek.top/card.php?random=https://www.vidbm.com/embed-ru7w5xremx5b.html"
        },
        {
          "name": "mp4upload | HD",
          "embed_url": "https://animelek.top/card.php?random=https://www.mp4upload.com/embed-fzhmptxbjqw3.html"
        },
        {
          "name": "file-upload | HD",
          "embed_url": "https://animelek.top/card.php?random=https://www.file-upload.com/embed-yb8iu2t0mh60.html"
        }
      ],
      "downloads": [
        {
          "server": "file-upload",
          "quality": "720p",
          "language": "مترجم",
          "url": "https://www.file-upload.com/yb8iu2t0mh60"
        },
        {
          "server": "drive",
          "quality": "720p",
          "language": "مترجم",
          "url": "https://drive.google.com/u/0/uc?id=1GDEUwRd5hMFZ3_WRGFbbtn5R0hVCl1Nn&export=download"
        },
        {
          "server": "mega",
          "quality": "720p",
          "language": "مترجم",
          "url": "https://mega.nz/file/qfIzASYJ#8By8ykPS73ITeZ97zUKtLIBB49EWOb9InrEXvrOhWbU"
        },
        {
          "server": "mp4upload",
          "quality": "720p",
          "language": "مترجم",
          "url": "https://www.mp4upload.com/fzhmptxbjqw3"
        },
        {
          "server": "uptobox",
          "quality": "720p",
          "language": "مترجم",
          "url": "https://uptobox.com/0onnwonvk9zs"
        },
        {
          "server": "solidfiles",
          "quality": "720p",
          "language": "مترجم",
          "url": "https://www.solidfiles.com/v/ABjWBz6Kk482P"
        },
        {
          "server": "letsupload",
          "quality": "720p",
          "language": "مترجم",
          "url": "https://letsupload.co/3zRTT/[Anime4up.com]_ZWNTC_EP_06_HD.mp4"
        }
      ]
    },
    {
      "number": "7",
      "title": "الأونا 7Zashiki Warashi no Tatami-chan",
      "date": "15 يوليو, 2020",
      "servers": [
        {
          "name": "solidfiles | HD",
          "embed_url": "https://animelek.top/card.php?random=https://www.solidfiles.com/e/Yqjmvgk48nzPg"
        },
        {
          "name": "ok ru | HD",
          "embed_url": "https://animelek.top/card.php?random=https://ok.ru/videoembed/1468715109082"
        },
        {
          "name": "google | HD",
          "embed_url": "https://animelek.top/card.php?random=https://drive.google.com/file/d/1tjxuBIKgZ_hduVuqV8FfzeeV7n1p4vSX/preview"
        },
        {
          "name": "4shared | HD",
          "embed_url": "https://animelek.top/card.php?random=https://www.4shared.com/web/embed/file/CS758bYliq"
        },
        {
          "name": "mega | HD",
          "embed_url": "https://animelek.top/card.php?random=https://mega.nz/embed/Td40HSBQ#pdHY2zL18DUBiK_FRhZizi7pprgYgzA2UWO7MtOj090"
        },
        {
          "name": "uptostream | HD",
          "embed_url": "https://animelek.top/card.php?random=https://uptostream.com/iframe/3kr924b3lnu5"
        },
        {
          "name": "vidbm | HD",
          "embed_url": "https://animelek.top/card.php?random=https://www.vidbm.com/embed-9aje76cxovk9.html"
        },
        {
          "name": "vidfast | HD",
          "embed_url": "https://animelek.top/card.php?random=https://vidfast.co/embed-1nhfkuppgp6t.html"
        },
        {
          "name": "mp4upload | HD",
          "embed_url": "https://animelek.top/card.php?random=https://www.mp4upload.com/embed-4nsajqa6ol38.html"
        },
        {
          "name": "file-upload | HD",
          "embed_url": "https://animelek.top/card.php?random=https://www.file-upload.com/embed-0ixho6sq4r2w.html"
        }
      ],
      "downloads": [
        {
          "server": "file-upload",
          "quality": "720p",
          "language": "مترجم",
          "url": "https://www.file-upload.com/0ixho6sq4r2w"
        },
        {
          "server": "drive",
          "quality": "720p",
          "language": "مترجم",
          "url": "https://drive.google.com/u/0/uc?id=1tjxuBIKgZ_hduVuqV8FfzeeV7n1p4vSX&export=download"
        },
        {
          "server": "mega",
          "quality": "720p",
          "language": "مترجم",
          "url": "https://mega.nz/file/Td40HSBQ#pdHY2zL18DUBiK_FRhZizi7pprgYgzA2UWO7MtOj090"
        },
        {
          "server": "mp4upload",
          "quality": "720p",
          "language": "مترجم",
          "url": "https://www.mp4upload.com/4nsajqa6ol38"
        },
        {
          "server": "uptobox",
          "quality": "720p",
          "language": "مترجم",
          "url": "https://uptobox.com/3kr924b3lnu5"
        },
        {
          "server": "solidfiles",
          "quality": "720p",
          "language": "مترجم",
          "url": "https://www.solidfiles.com/v/Yqjmvgk48nzPg"
        },
        {
          "server": "4shared",
          "quality": "720p",
          "language": "مترجم",
          "url": "https://www.4shared.com/video/CS758bYliq/Anime4upcom_ZWNTC_EP_07_HD.html"
        }
      ]
    },
    {
      "number": "4",
      "title": "الأونا 4Zashiki Warashi no Tatami-chan",
      "date": "15 يوليو, 2020",
      "servers": [
        {
          "name": "ok ru | HD",
          "embed_url": "https://animelek.top/card.php?random=https://ok.ru/videoembed/1445189454554"
        },
        {
          "name": "letsupload | HD",
          "embed_url": "https://animelek.top/card.php?random=https://letsupload.co/plugins/mediaplayer/site/_embed.php?u=1xsgd&w=640&h=320"
        },
        {
          "name": "google | HD",
          "embed_url": "https://animelek.top/card.php?random=https://drive.google.com/file/d/1VUxLm-KQOZRPlMu4rFsLfRicvNi4tis8/preview"
        },
        {
          "name": "solidfiles | HD",
          "embed_url": "https://animelek.top/card.php?random=https://www.solidfiles.com/e/yZPd3MevZg2XL"
        },
        {
          "name": "4shared | HD",
          "embed_url": "https://animelek.top/card.php?random=https://www.4shared.com/web/embed/file/85OibFIEea"
        },
        {
          "name": "mega | HD",
          "embed_url": "https://animelek.top/card.php?random=https://mega.nz/embed/BmBHDYiT#1eaOfFAOlfG3E18w5ZDjh3vCLoeKSKjRtODIuTzKhxM"
        },
        {
          "name": "uptostream | HD",
          "embed_url": "https://animelek.top/card.php?random=https://uptostream.com/iframe/mzqushwgijdc"
        },
        {
          "name": "vidbm | HD",
          "embed_url": "https://animelek.top/card.php?random=https://www.vidbm.com/embed-b3n7omwpqf5n.html"
        },
        {
          "name": "mp4upload | HD",
          "embed_url": "https://animelek.top/card.php?random=https://www.mp4upload.com/embed-cxf7g8w6tycs.html"
        },
        {
          "name": "file-up org | HD",
          "embed_url": "https://animelek.top/card.php?random=https://www.file-up.org/embed-vo4v7hjshx36.html"
        }
      ],
      "downloads": [
        {
          "server": "file-up",
          "quality": "720p",
          "language": "مترجم",
          "url": "https://www.file-up.org/vo4v7hjshx36"
        },
        {
          "server": "drive",
          "quality": "720p",
          "language": "مترجم",
          "url": "https://drive.google.com/u/0/uc?id=1VUxLm-KQOZRPlMu4rFsLfRicvNi4tis8&export=download"
        },
        {
          "server": "mega",
          "quality": "720p",
          "language": "مترجم",
          "url": "https://mega.nz/file/BmBHDYiT#1eaOfFAOlfG3E18w5ZDjh3vCLoeKSKjRtODIuTzKhxM"
        },
        {
          "server": "mp4upload",
          "quality": "720p",
          "language": "مترجم",
          "url": "https://www.mp4upload.com/cxf7g8w6tycs"
        },
        {
          "server": "uptobox",
          "quality": "720p",
          "language": "مترجم",
          "url": "https://uptobox.com/mzqushwgijdc"
        },
        {
          "server": "solidfiles",
          "quality": "720p",
          "language": "مترجم",
          "url": "https://www.solidfiles.com/v/yZPd3MevZg2XL"
        },
        {
          "server": "letsupload",
          "quality": "720p",
          "language": "مترجم",
          "url": "https://letsupload.co/1xsgd/[Anime4up.com]_ZWNTC_EP_04_HD.mp4"
        },
        {
          "server": "4shared",
          "quality": "720p",
          "language": "مترجم",
          "url": "https://www.4shared.com/video/85OibFIEea/Anime4upcom_ZWNTC_EP_04_HD.html"
        }
      ]
    },
    {
      "number": "5",
      "title": "الأونا 5Zashiki Warashi no Tatami-chan",
      "date": "15 يوليو, 2020",
      "servers": [
        {
          "name": "ok ru | HD",
          "embed_url": "https://animelek.top/card.php?random=https://ok.ru/videoembed/1451191765722"
        },
        {
          "name": "google | HD",
          "embed_url": "https://animelek.top/card.php?random=https://drive.google.com/file/d/11HghZCx0yZd7d6KdEI_I7DPiXRNRmXgn/preview"
        },
        {
          "name": "solidfiles | HD",
          "embed_url": "https://animelek.top/card.php?random=https://www.solidfiles.com/e/Gv6VaNKjxWGnx"
        },
        {
          "name": "4shared | HD",
          "embed_url": "https://animelek.top/card.php?random=https://www.4shared.com/web/embed/file/28vc-Xrnea"
        },
        {
          "name": "mega | HD",
          "embed_url": "https://animelek.top/card.php?random=https://mega.nz/embed/Cn5XzBZC#xGDqIhFhOJdICUN3l23-5Kn8tJrbiHQcljyPcaKqcb0"
        },
        {
          "name": "uptostream | HD",
          "embed_url": "https://animelek.top/card.php?random=https://uptostream.com/iframe/jbhmll9qxwv5"
        },
        {
          "name": "vidbm | HD",
          "embed_url": "https://animelek.top/card.php?random=https://www.vidbm.com/embed-b5k51o0xy6kw.html"
        },
        {
          "name": "mp4upload | HD",
          "embed_url": "https://animelek.top/card.php?random=https://www.mp4upload.com/embed-qrkezeylzoyf.html"
        },
        {
          "name": "file-up org | HD",
          "embed_url": "https://animelek.top/card.php?random=https://www.file-up.org/embed-ftd0bxmxvy0a.html"
        }
      ],
      "downloads": [
        {
          "server": "file-up",
          "quality": "720p",
          "language": "مترجم",
          "url": "https://www.file-up.org/ftd0bxmxvy0a"
        },
        {
          "server": "drive",
          "quality": "720p",
          "language": "مترجم",
          "url": "https://drive.google.com/u/0/uc?id=11HghZCx0yZd7d6KdEI_I7DPiXRNRmXgn&export=download"
        },
        {
          "server": "mega",
          "quality": "720p",
          "language": "مترجم",
          "url": "https://mega.nz/file/Cn5XzBZC#xGDqIhFhOJdICUN3l23-5Kn8tJrbiHQcljyPcaKqcb0"
        },
        {
          "server": "mp4upload",
          "quality": "720p",
          "language": "مترجم",
          "url": "https://www.mp4upload.com/qrkezeylzoyf"
        },
        {
          "server": "uptobox",
          "quality": "720p",
          "language": "مترجم",
          "url": "https://uptobox.com/jbhmll9qxwv5"
        },
        {
          "server": "solidfiles",
          "quality": "720p",
          "language": "مترجم",
          "url": "https://www.solidfiles.com/v/Gv6VaNKjxWGnx"
        },
        {
          "server": "letsupload",
          "quality": "720p",
          "language": "مترجم",
          "url": "https://letsupload.co/3zBle/[Anime4up.com]_ZWNTC_EP_05_HD.mp4"
        },
        {
          "server": "4shared",
          "quality": "720p",
          "language": "مترجم",
          "url": "https://www.4shared.com/video/28vc-Xrnea/Anime4upcom_ZWNTC_EP_05_HD.html"
        }
      ]
    },
    {
      "number": "3",
      "title": "الأونا 3Zashiki Warashi no Tatami-chan",
      "date": "15 يوليو, 2020",
      "servers": [
        {
          "name": "ok ru | HD",
          "embed_url": "https://animelek.top/card.php?random=https://ok.ru/videoembed/1445177920218"
        },
        {
          "name": "letsupload | HD",
          "embed_url": "https://animelek.top/card.php?random=https://letsupload.co/plugins/mediaplayer/site/_embed.php?u=1xsec&w=640&h=320"
        },
        {
          "name": "google | HD",
          "embed_url": "https://animelek.top/card.php?random=https://drive.google.com/file/d/1Yo1xNjZ-WmlAjSvZxZ-2bHkWdAjHlJmt/preview"
        },
        {
          "name": "solidfiles | HD",
          "embed_url": "https://animelek.top/card.php?random=https://www.solidfiles.com/e/Zj7ApgNDBN2wg"
        },
        {
          "name": "4shared | HD",
          "embed_url": "https://animelek.top/card.php?random=https://www.4shared.com/web/embed/file/n0Z9e7FFiq"
        },
        {
          "name": "mega | HD",
          "embed_url": "https://animelek.top/card.php?random=https://mega.nz/embed/5nhmgKha#6R1fuF4l1zujyE8p3OhBO5VgI0alnIfxDbppumHCxwo"
        },
        {
          "name": "uptostream | HD",
          "embed_url": "https://animelek.top/card.php?random=https://uptostream.com/iframe/dla7ddm92ml8"
        },
        {
          "name": "vidbm | HD",
          "embed_url": "https://animelek.top/card.php?random=https://www.vidbm.com/embed-mphf56ytcdp6.html"
        },
        {
          "name": "mp4upload | HD",
          "embed_url": "https://animelek.top/card.php?random=https://www.mp4upload.com/embed-ly2aj9atcdz7.html"
        },
        {
          "name": "file-up org | HD",
          "embed_url": "https://animelek.top/card.php?random=https://www.file-up.org/embed-oem2cb6xbw95.html"
        }
      ],
      "downloads": [
        {
          "server": "file-up",
          "quality": "720p",
          "language": "مترجم",
          "url": "https://www.file-up.org/oem2cb6xbw95"
        },
        {
          "server": "drive",
          "quality": "720p",
          "language": "مترجم",
          "url": "https://drive.google.com/u/0/uc?id=1Yo1xNjZ-WmlAjSvZxZ-2bHkWdAjHlJmt&export=download"
        },
        {
          "server": "mega",
          "quality": "720p",
          "language": "مترجم",
          "url": "https://mega.nz/file/5nhmgKha#6R1fuF4l1zujyE8p3OhBO5VgI0alnIfxDbppumHCxwo"
        },
        {
          "server": "mp4upload",
          "quality": "720p",
          "language": "مترجم",
          "url": "https://www.mp4upload.com/ly2aj9atcdz7"
        },
        {
          "server": "uptobox",
          "quality": "720p",
          "language": "مترجم",
          "url": "https://uptobox.com/dla7ddm92ml8"
        },
        {
          "server": "solidfiles",
          "quality": "720p",
          "language": "مترجم",
          "url": "https://www.solidfiles.com/v/Zj7ApgNDBN2wg"
        },
        {
          "server": "letsupload",
          "quality": "720p",
          "language": "مترجم",
          "url": "https://letsupload.co/1xsec/[Anime4up.com]_ZWNTC_EP_03_HD.mp4"
        },
        {
          "server": "4shared",
          "quality": "720p",
          "language": "مترجم",
          "url": "https://www.4shared.com/video/n0Z9e7FFiq/Anime4upcom_ZWNTC_EP_03_HD.html"
        }
      ]
    },
    {
      "number": "2",
      "title": "الأونا 2Zashiki Warashi no Tatami-chan",
      "date": "15 يوليو, 2020",
      "servers": [
        {
          "name": "ok ru | HD",
          "embed_url": "https://animelek.top/card.php?random=https://ok.ru/videoembed/1430688041690"
        },
        {
          "name": "google | HD",
          "embed_url": "https://animelek.top/card.php?random=https://drive.google.com/file/d/1ZEyGqXhfNmLcYodG20qblailsjb3ClHQ/preview"
        },
        {
          "name": "letsupload | HD",
          "embed_url": "https://animelek.top/card.php?random=https://letsupload.co/plugins/mediaplayer/site/_embed.php?u=3yK2v&w=640&h=320"
        },
        {
          "name": "solidfiles | HD",
          "embed_url": "https://animelek.top/card.php?random=https://www.solidfiles.com/e/38kpR3vqK2ve4"
        },
        {
          "name": "4shared | HD",
          "embed_url": "https://animelek.top/card.php?random=https://www.4shared.com/web/embed/file/iDIoKHziiq"
        },
        {
          "name": "mega | HD",
          "embed_url": "https://animelek.top/card.php?random=https://mega.nz/embed/59MBkQ6J#vIiQ7p3Iqb4Vk2uYe0w5MD1BhDQeQZ0y4EhGo8hGLqI"
        },
        {
          "name": "uptostream | HD",
          "embed_url": "https://animelek.top/card.php?random=https://uptostream.com/iframe/68crv6od84o9"
        },
        {
          "name": "vidbm | HD",
          "embed_url": "https://animelek.top/card.php?random=https://www.vidbm.com/embed-0eu2ahk3518p.html"
        },
        {
          "name": "mp4upload | HD",
          "embed_url": "https://animelek.top/card.php?random=https://www.mp4upload.com/embed-ppzre26640v6.html"
        },
        {
          "name": "file-up org | HD",
          "embed_url": "https://animelek.top/card.php?random=https://www.file-up.org/embed-pogo4ibk5blp.html"
        }
      ],
      "downloads": [
        {
          "server": "file-up",
          "quality": "720p",
          "language": "مترجم",
          "url": "https://www.file-up.org/pogo4ibk5blp"
        },
        {
          "server": "drive",
          "quality": "720p",
          "language": "مترجم",
          "url": "https://drive.google.com/u/0/uc?id=1ZEyGqXhfNmLcYodG20qblailsjb3ClHQ&export=download"
        },
        {
          "server": "mega",
          "quality": "720p",
          "language": "مترجم",
          "url": "https://mega.nz/file/59MBkQ6J#vIiQ7p3Iqb4Vk2uYe0w5MD1BhDQeQZ0y4EhGo8hGLqI"
        },
        {
          "server": "mp4upload",
          "quality": "720p",
          "language": "مترجم",
          "url": "https://www.mp4upload.com/ppzre26640v6"
        },
        {
          "server": "uptobox",
          "quality": "720p",
          "language": "مترجم",
          "url": "https://uptobox.com/68crv6od84o9"
        },
        {
          "server": "solidfiles",
          "quality": "720p",
          "language": "مترجم",
          "url": "https://www.solidfiles.com/v/38kpR3vqK2ve4"
        },
        {
          "server": "letsupload",
          "quality": "720p",
          "language": "مترجم",
          "url": "https://letsupload.co/3yK2v/[Anime4up.com]_ZWNTC_EP_02_HD.mp4"
        },
        {
          "server": "4shared",
          "quality": "720p",
          "language": "مترجم",
          "url": "https://www.4shared.com/video/iDIoKHziiq/Anime4upcom_ZWNTC_EP_02_HD.html"
        }
      ]
    },
    {
      "number": "1",
      "title": "الأونا 1Zashiki Warashi no Tatami-chan",
      "date": "15 يوليو, 2020",
      "servers": [
        {
          "name": "ok ru | HD",
          "embed_url": "https://animelek.top/card.php?random=https://ok.ru/videoembed/1420957977306"
        },
        {
          "name": "google | HD",
          "embed_url": "https://animelek.top/card.php?random=https://drive.google.com/file/d/1yJQxlNR9GAgdX0wBXn0MusFGHxogPHNu/preview"
        },
        {
          "name": "letsupload | HD",
          "embed_url": "https://animelek.top/card.php?random=https://letsupload.co/plugins/mediaplayer/site/_embed.php?u=3yt6n&w=640&h=320"
        },
        {
          "name": "solidfiles | HD",
          "embed_url": "https://animelek.top/card.php?random=https://www.solidfiles.com/e/p5YW2enxKjKyd"
        },
        {
          "name": "4shared | HD",
          "embed_url": "https://animelek.top/card.php?random=https://www.4shared.com/web/embed/file/EenMuB0Kea"
        },
        {
          "name": "mega | HD",
          "embed_url": "https://animelek.top/card.php?random=https://mega.nz/embed/ZjAQFQIT#FiMLNqr8UhQg9fUALRsR3NigLKo6XkaB6C7-ZQZW5JQ"
        },
        {
          "name": "uptostream | HD",
          "embed_url": "https://animelek.top/card.php?random=https://uptostream.com/iframe/b3gydvern7nv"
        },
        {
          "name": "vidbm | HD",
          "embed_url": "https://animelek.top/card.php?random=https://www.vidbm.com/embed-2nr3rqszhnwm.html"
        },
        {
          "name": "mp4upload | HD",
          "embed_url": "https://animelek.top/card.php?random=https://www.mp4upload.com/embed-jjeol3q8vs3w.html"
        },
        {
          "name": "file-up org | HD",
          "embed_url": "https://animelek.top/card.php?random=https://www.file-up.org/embed-uc3jnjhnahcw.html"
        }
      ],
      "downloads": [
        {
          "server": "file-up",
          "quality": "720p",
          "language": "مترجم",
          "url": "https://www.file-up.org/uc3jnjhnahcw"
        },
        {
          "server": "drive",
          "quality": "720p",
          "language": "مترجم",
          "url": "https://drive.google.com/u/0/uc?id=1yJQxlNR9GAgdX0wBXn0MusFGHxogPHNu&export=download"
        },
        {
          "server": "mega",
          "quality": "720p",
          "language": "مترجم",
          "url": "https://mega.nz/file/ZjAQFQIT#FiMLNqr8UhQg9fUALRsR3NigLKo6XkaB6C7-ZQZW5JQ"
        },
        {
          "server": "mp4upload",
          "quality": "720p",
          "language": "مترجم",
          "url": "https://www.mp4upload.com/jjeol3q8vs3w"
        },
        {
          "server": "uptobox",
          "quality": "720p",
          "language": "مترجم",
          "url": "https://uptobox.com/b3gydvern7nv"
        },
        {
          "server": "solidfiles",
          "quality": "720p",
          "language": "مترجم",
          "url": "https://www.solidfiles.com/v/p5YW2enxKjKyd"
        },
        {
          "server": "letsupload",
          "quality": "720p",
          "language": "مترجم",
          "url": "https://letsupload.co/3yt6n/[Anime4up.com]_ZWNTC_EP_01_HD.mp4"
        },
        {
          "server": "4shared",
          "quality": "720p",
          "language": "مترجم",
          "url": "https://www.4shared.com/video/EenMuB0Kea/Anime4upcom_ZWNTC_EP_01_HD.html"
        }
      ]
    }
  ],
  "last_updated": "2026-06-25T03:44:48.264930"
}